Workbook

Sheet Assumptions & Funding
A1: COGNITRONICS — ASSUMPTIONS & FUNDING
A2: Validated model conventions, financing terms and linked operating-cost baseline · 18-month pre-seed plan
A4: MODEL FRAME
A5: Model horizon | B5: 18 | C5: operating months : | D5: M1–M18 | E5: M0 is the financing event
A6: Model currency | B6: EUR (€) | C6: Reporting and cash-planning currency
A7: USD → EUR planning FX | B7: 0.93 | C7: $1 = €0.93
A8: Round target (USD) | B8: =SUM(C15:C17) -> 750000
A9: Funding envelope (EUR) | B9: =B8*B7 -> 697500
A10: Opening cash before first close | B10: 0 | C10: M0 before initial SAFE inflow
A11: Funding timing | B11: Scenario-driven | C11: Closing months will be editable in Runway & Scenarios
A13: SAFE ROUND TERMS
A14: Tier | B14: Order | C14: Allocation (USD) | D14: Allocation (EUR) | E14: Valuation Cap (USD) | F14: Instrument | G14: Terms | H14: Status
A15: Tier 1 | B15: 1 | C15: 200000 | D15: =C15*$B$7 -> 186000 | E15: 6000000 | F15: YC post-money SAFE | G15: Cap only · no discount · no MFN · no automatic pro-rata | H15: Validated
A16: Tier 2 | B16: 2 | C16: 250000 | D16: =C16*$B$7 -> 232500 | E16: 7500000 | F16: YC post-money SAFE | G16: Cap only · no discount · no MFN · no automatic pro-rata | H16: Validated
A17: Tier 3 | B17: 3 | C17: 300000 | D17: =C17*$B$7 -> 279000 | E17: 9000000 | F17: YC post-money SAFE | G17: Cap only · no discount · no MFN · no automatic pro-rata | H17: Validated
A18: TOTAL ROUND | C18: =SUM(C15:C17) -> 750000 | D18: =SUM(D15:D17) -> 697500 | F18: Standard SAFE at valuation cap | H18: LOCKED
A20: OPERATING & TAX CONVENTIONS
A21: Assumption | B21: Value | C21: Timing | D21: Classification | E21: Source / Note
A22: Operating plan length | B22: 18 | C22: M1–M18 | D22: Cash plan | E22: M0 is separate and represents the financing event.
A23: VAT recovery | B23: Conservative annual refund | C23: M13 for M1–M12 | D23: Working capital | E23: Apply only to invoice-level deductible VAT; M13–M18 recoverable VAT remains outstanding at plan end.
A24: CIR, grants and subsidies | B24: Excluded | C24: Base case | D24: No cash inflow | E24: Potential upside is not used to finance the base plan.
A25: HQ furniture, fit-out and appliances | B25: 5000 | C25: M1 | D25: CapEx | E25: Validated provision in HQ & lab est.
A26: Corporate liability, cyber and D&O insurance | B26: 4000 | C26: €2K M1 + €2K M13 | D26: OpEx | E26: Validated 18-month cash provision in Other expenses.
A27: Contingency policy | B27: Category-specific only | C27: Throughout | D27: Reserve | E27: Keep existing schedule-level contingencies; do not apply a second blanket contingency.
A28: Unallocated strategic reserve | B28: Funding less modeled expenditure | C28: M18 | D28: Liquidity | E28: Displayed separately and not treated as an operating expense.
A30: LINKED 18-MONTH COST BASE
A31: Schedule | B31: Total 12M | C31: Total 18M | D31: % of 18M spend | E31: Cost basis | F31: Source cell | G31: Status | H31: Notes
A32: Hiring & Compensation Plan | B32: ='Hiring & Compensation Plan'!W27 -> 207204.58 | C32: ='Hiring & Compensation Plan'!X27 -> 337743.58 | D32: =IF($C$36=0,0,C32/$C$36) -> 0.51677866 | E32: Employer cost | F32: Hiring & Compensation Plan!W27:X27 | G32: LINKED | H32: Includes fractional CTO
A33: MVP & lab hardware BOM | B33: ='MVP & lab hardware BOM'!V70 -> 61464.82 | C33: ='MVP & lab hardware BOM'!W70 -> 81897 | D33: =IF($C$36=0,0,C33/$C$36) -> 0.12530992 | E33: CapEx + technical OpEx | F33: MVP & lab hardware BOM!V70:W70 | G33: LINKED | H33: HT basis; VAT handled separately
A34: HQ & lab est. | B34: ='HQ & lab est.'!V31 -> 105365 | C34: ='HQ & lab est.'!W31 -> 148835 | D34: =IF($C$36=0,0,C34/$C$36) -> 0.22773121 | E34: Occupancy + hosting | F34: HQ & lab est.!V31:W31 | G34: LINKED | H34: Includes recoverable security deposit
A35: Other expenses | B35: ='Other expenses'!V35 -> 55100 | C35: ='Other expenses'!W35 -> 85080 | D35: =IF($C$36=0,0,C35/$C$36) -> 0.13018021 | E35: Strategic operations | F35: Other expenses!V35:W35 | G35: LINKED | H35: Includes annual corporate insurance
A36: TOTAL MODELED EXPENDITURE | B36: =SUM(B32:B35) -> 429134.4 | C36: =SUM(C32:C35) -> 653555.58 | D36: 1 | G36: RECONCILED
A37: FUNDING ENVELOPE | C37: =$B$9 -> 697500
A38: UNALLOCATED STRATEGIC RESERVE | C38: =C37-C36 -> 43944.42 | D38: =IF(C37=0,0,C38/C37) -> 0.063002753
A39: AVERAGE MONTHLY MODELED BURN | C39: =C36/$B$5 -> 36308.643
A41: MODEL CONTROLS
A42: Check | B42: Expected | C42: Actual | D42: Difference | E42: Status | F42: Notes
A43: SAFE allocations equal round target | B43: 750000 | C43: =$B$8 -> 750000 | D43: =C43-B43 -> 0 | E43: =IF(ABS(D43)<=1,"PASS","REVIEW") -> PASS | F43: Tier allocations must total $750K.
A44: EUR funding conversion | B44: 697500 | C44: =$B$9 -> 697500 | D44: =C44-B44 -> 0 | E44: =IF(ABS(D44)<=1,"PASS","REVIEW") -> PASS | F44: $750K × 0.93.
A45: SAFE tier count | B45: 3 | C45: =COUNTA(A15:A17) -> 3 | D45: =C45-B45 -> 0 | E45: =IF(D45=0,"PASS","REVIEW") -> PASS | F45: Three sequential pricing tiers.
A46: Planned expenditure within funding | B46: 0 | C46: =C37-C36 -> 43944.42 | D46: =C46-B46 -> 43944.42 | E46: =IF(C46>=0,"PASS","REVIEW") -> PASS | F46: Positive value is the unallocated reserve.
A47: OVERALL MODEL STATUS | E47: =IF(COUNTIF(E43:E46,"PASS")=4,"PASS","REVIEW") -> PASS | F47: All current funding and linked-cost controls must pass.
A49: LEGEND & GOVERNANCE
A50: Blue text = | B50: Validated hardcode / editable assumption | C50: Green text = | D50: Linked from source tab | E50: Black text = | F50: Formula | G50: Yellow fill = | H50: Requires review
A51: Version : | B51: Investor integration v1 | C51: Validated : | D51: 2026-08-14 | E51: Owner : | F51: Cognitronics | G51: Stage : | H51: Step 1 complete

Sheet Cap Table & Equity Plan
A1: COGNICS SYSTEMS, INC. — CAP TABLE & EQUITY PLAN
A2: Legal ownership, equity reserves, planned core-team grants and proposed SAFE dilution · investor diligence view
A3: Legal ownership, reserved equity, planned grants, and pro forma financing outcomes are shown separately. Core-team allocations and SAFE outcomes are illustrative planning assumptions only; they are not current legal ownership, executed grants, or issued securities. All future grants remain subject to board approval, definitive documentation, applicable tax and legal review, and the terms of any future financing.
A5: 1. LEGAL OWNERSHIP TODAY — DELAWARE PARENT
A6: Metric | B6: Value | C6: Unit / Ownership | D6: Legal status | E6: Details | F6: Source / Control
A7: Authorized common shares | B7: 10000000 | C7: shares | D7: Authorized | E7: Cognics Systems, Inc. authorized common stock. | F7: Corporate records
A8: Issued common shares | B8: 9000000 | C8: shares | D8: Issued | E8: All issued shares are restricted common stock. | F8: Executed Founder Restricted Stock Purchase Agreement
A9: Legal holder | B9: THMS / Thomas Manrique | C9: 0.9 | D9: Current legal ownership | E9: 100% of issued shares; no other current legal stockholders. | F9: Issued-share ledger
A10: Legal issued ownership | B10: 0.9 | C10: of issued shares | D10: Current / legal | E10: Calculated against 9,000,000 issued common shares. | F10: 9,000,000 ÷ 9,000,000
A11: Founder restricted common stock | B11: 9000000 | C11: shares | D11: Issued / restricted | E11: Subject to company repurchase rights over unvested shares. | F11: Executed founder RSA
A12: Founder vesting commencement | B12: =DATE(2026,2,1) -> 46054 | C12: date | D12: Binding / executed | E12: Four-year vesting with a 12-month cliff. | F12: Executed founder RSA
A13: Founder vesting terms | B13: 48 months | C13: 12-month cliff | D13: Binding / executed | E13: 12/48 vest on Feb 1, 2027; 1/48 monthly thereafter. | F13: Executed founder RSA
A14: Current fully diluted planning view | B14: 10000000 | C14: illustrative units | D14: Pro forma only | E14: THMS 90% / ESOP reserve 10%; no team grants or SAFE shares are issued. | F14: Planning denominator ≠ legal issued shares
A15: French operating subsidiary | B15: Future French SASU | C15: 1 | D15: Wholly owned by parent | E15: No founder, core-team or SAFE ownership is modeled at SASU level. | F15: Cognics Systems, Inc. remains financing vehicle and owner of core IP.
A16: 2. RESERVED AND UNISSUED INSTRUMENTS
A17: Instrument | B17: Reserved amount | C17: % of planning denominator | D17: Issued today? | E17: Status | F17: Notes
A18: ESOP reserve | B18: 1000000 | C18: =B18/$B$7 -> 0.1 | D18: No | E18: Reserved / unissued | F18: Separate 10% reserve for broader employees, advisors and future grants; not part of the core-team target pool.
A19: SAFE conversion reserve | B19: TBD at conversion | C19: =$D$39 -> 0.1 | D19: No | E19: Board-authorized reserve | F19: No SAFE shares currently issued. Conversion mechanics and resulting legal share count remain TBD; modeled only in the pro forma scenario.
A20: Reserved ≠ issued. The ESOP reserve and future SAFE conversion reserve do not constitute current legal ownership.
A22: 3. PLANNED CORE-TEAM ALLOCATION
A23: Holder / Pool | B23: Role | C23: Illustrative planning units | D23: Pre-SAFE normalized ownership | E23: Post-SAFE target % | F23: Legal status | G23: Mechanism / Notes
A24: THMS | B24: Founder | C24: 4000000 | D24: =E24/SUM($E$24:$E$29) -> 0.44444444 | E24: 0.4 | F24: Retained target; planning-only | G24: Founder retained target following planned reallocation; current legal ownership remains 100% of issued shares.
A25: JSPH | B25: AI / Robotics | C25: 1500000 | D25: =E25/SUM($E$24:$E$29) -> 0.16666667 | E25: 0.15 | F25: Illustrative / ungranted | G25: Planned founder reallocation / future restricted-stock grant; subject to board approval and individual RSA execution.
A26: DALI | B26: Maths Applied | C26: 500000 | D26: =E26/SUM($E$24:$E$29) -> 0.055555556 | E26: 0.05 | F26: Illustrative / ungranted | G26: Planned founder reallocation / future restricted-stock grant; subject to board approval and individual RSA execution.
A27: NADR | B27: Embedded Systems | C27: 1000000 | D27: =E27/SUM($E$24:$E$29) -> 0.11111111 | E27: 0.1 | F27: Illustrative / ungranted | G27: Planned founder reallocation / future restricted-stock grant; subject to board approval and individual RSA execution.
A28: NEXT (future key Hire) | B28: AI / Robotics | C28: 1000000 | D28: =E28/SUM($E$24:$E$29) -> 0.11111111 | E28: 0.1 | F28: Illustrative / ungranted | G28: Separate key-hire target; not part of the ESOP reserve. Future RSA or option terms remain unexecuted.
A29: ESOP | B29: Broader employees / advisors | C29: 1000000 | D29: =E29/SUM($E$24:$E$29) -> 0.11111111 | E29: 0.1 | F29: Reserved / unissued | G29: Separate company reserve; not a current grant or legal ownership.
A30: CORE-TEAM AGGREGATE | B30: JSPH + DALI + NADR + future key hire | C30: =SUM(C25:C28) -> 4000000 | D30: =SUM(D25:D28) -> 0.44444444 | E30: =SUM(E25:E28) -> 0.4 | F30: Illustrative / ungranted | G30: 40% aggregate post-SAFE target.
A31: TOTAL PRE-SAFE PLANNED HOLDERS | B31: Founder + core team + ESOP | C31: =SUM(C24:C29) -> 9000000 | D31: =SUM(D24:D29) -> 1 | E31: =SUM(E24:E29) -> 0.9 | F31: Planning reconciliation | G31: Pre-SAFE normalized ownership is 100%; stated post-SAFE targets occupy 90%, before the 10% SAFE scenario.
A32: The 10,000,000-unit denominator is an illustrative fully diluted planning convention, not a representation that planned core-team grants or SAFE securities have been legally issued.
A34: 4. PROPOSED SAFE DILUTION
A35: Tier | B35: Investment amount (USD) | C35: Post-money cap (USD) | D35: Implied FD ownership | E35: Status | F35: Terms / Source
A36: Tier 1 | B36: ='Assumptions & Funding'!C15 -> 200000 | C36: ='Assumptions & Funding'!E15 -> 6000000 | D36: =B36/C36 -> 0.033333333 | E36: Proposed / unclosed | F36: YC post-money SAFE · cap only · no discount · no MFN · no automatic pro-rata
A37: Tier 2 | B37: ='Assumptions & Funding'!C16 -> 250000 | C37: ='Assumptions & Funding'!E16 -> 7500000 | D37: =B37/C37 -> 0.033333333 | E37: Proposed / unclosed | F37: YC post-money SAFE · cap only · no discount · no MFN · no automatic pro-rata
A38: Tier 3 | B38: ='Assumptions & Funding'!C17 -> 300000 | C38: ='Assumptions & Funding'!E17 -> 9000000 | D38: =B38/C38 -> 0.033333333 | E38: Proposed / unclosed | F38: YC post-money SAFE · cap only · no discount · no MFN · no automatic pro-rata
A39: TOTAL PROPOSED SAFE | B39: =SUM(B36:B38) -> 750000 | D39: =SUM(D36:D38) -> 0.1 | E39: Board-approved up to $750K | F39: No SAFEs issued, signed, closed, funded or converted as of the current model date.
A40: SAFE conversion is assumed only in the pro forma post-SAFE scenario. Illustrative ownership is calculated as investment ÷ post-money valuation cap.
A42: 5. PRO FORMA POST-SAFE OWNERSHIP
A43: Owner group | B43: Illustrative planning units | C43: Post-SAFE ownership | D43: Status | E43: Notes
A44: Founder THMS | B44: 4000000 | C44: =B44/$B$48 -> 0.4 | D44: Illustrative post-SAFE | E44: Founder target; not current legal issued ownership.
A45: Core team aggregate JSPH + DALI + NADR + KeyHire | B45: 4000000 | C45: =B45/$B$48 -> 0.4 | D45: Illustrative / ungranted | E45: JSPH 15% + DALI 5% + NADR 10% + future key hire 10%.
A46: ESOP | B46: 1000000 | C46: =B46/$B$48 -> 0.1 | D46: Reserved / unissued | E46: Separate 10% reserve.
A47: SAFE investors | B47: 1000000 | C47: =B47/$B$48 -> 0.1 | D47: Proposed / unclosed | E47: Illustrative conversion units only; no SAFE shares currently issued.
A48: TOTAL | B48: =SUM(B44:B47) -> 10000000 | C48: =SUM(C44:C47) -> 1 | D48: Reconciled | E48: Illustrative fully diluted planning denominator.
A49: This table is the sole source for the ownership chart below and must not be interpreted as the current legal cap table.
A51: 6. VESTING SCHEDULES
A52: FOUNDER — BINDING, EXECUTED FOUR-YEAR SCHEDULE
A53: Metric | B53: Value | C53: Status | D53: Notes
A54: Restricted common shares | B54: 9000000 | C54: Issued / restricted | D54: Subject to company repurchase rights over unvested shares.
A55: Vesting commencement | B55: =DATE(2026,2,1) -> 46054 | C55: Binding / executed | D55: Founder RSA commencement date.
A56: Total vesting period | B56: 48 | C56: months | D56: Four years.
A57: Cliff period | B57: 12 | C57: months | D57: No scheduled vesting before the cliff date.
A58: Cliff vesting | B58: 0.25 | C58: 12/48 | D58: Vests on February 1, 2027.
A59: Monthly vesting thereafter | B59: =1/48 -> 0.020833333 | C59: per month | D59: Vests monthly after the cliff until fully vested.
A60: Unvested share treatment | B60: Company repurchase right | C60: Binding / executed | D60: Applies to unvested founder restricted common shares.
A62: CORE TEAM — ILLUSTRATIVE SEVEN-YEAR PROGRESSIVE / BACK-LOADED SCHEDULE
A63: Vesting year | B63: Incremental vesting | C63: Cumulative vesting | D63: Status | E63: Timing / Notes
A64: Year 1 / cliff | B64: 0 | C64: 0 | D64: Illustrative / unexecuted | E64: From each person’s own PRE-VAL start date.
A65: Year 2 | B65: 0.05 | C65: =C64+B65 -> 0.05 | D65: Illustrative / unexecuted | E65: Subject to individual negotiation and definitive documentation.
A66: Year 3 | B66: 0.1 | C66: =C65+B66 -> 0.15 | D66: Illustrative / unexecuted | E66: Subject to individual negotiation and definitive documentation.
A67: Year 4 | B67: 0.15 | C67: =C66+B67 -> 0.3 | D67: Illustrative / unexecuted | E67: Subject to individual negotiation and definitive documentation.
A68: Year 5 | B68: 0.2 | C68: =C67+B68 -> 0.5 | D68: Illustrative / unexecuted | E68: Subject to individual negotiation and definitive documentation.
A69: Year 6 | B69: 0.25 | C69: =C68+B69 -> 0.75 | D69: Illustrative / unexecuted | E69: Subject to individual negotiation and definitive documentation.
A70: Year 7 | B70: 0.25 | C70: =C69+B70 -> 1 | D70: Illustrative / unexecuted | E70: May change based on role, negotiation, board approval, counsel input and signed RSA or option agreement.
A71: Founder vesting is governed by the executed four-year RSA schedule above. The illustrative seven-year core-team schedule does not apply to THMS.
A72: Nota Bene : Legal ownership, reserved equity, planned grants, and pro forma financing outcomes are shown separately. Core-team allocations and SAFE outcomes are illustrative planning assumptions only; they are not current legal ownership, executed grants, or issued securities. All future grants remain subject to board approval, definitive documentation, applicable tax and legal review, and the terms of any future financing.
A74: 7. RECONCILIATION CHECKS
A75: Check | B75: Expected | C75: Actual | D75: Difference | E75: Status | F75: Notes
A76: Legal issued shares total | B76: 9000000 | C76: =$B$8 -> 9000000 | D76: =C76-B76 -> 0 | E76: =IF(ABS(D76)<0.5,"PASS","REVIEW") -> PASS | F76: Issued-share ledger control.
A77: Authorized common shares | B77: 10000000 | C77: =$B$7 -> 10000000 | D77: =C77-B77 -> 0 | E77: =IF(ABS(D77)<0.5,"PASS","REVIEW") -> PASS | F77: Corporate authorization control.
A78: Fully diluted planning model | B78: 10000000 | C78: =$B$48 -> 10000000 | D78: =C78-B78 -> 0 | E78: =IF(ABS(D78)<0.5,"PASS","REVIEW") -> PASS | F78: Illustrative units, not legal issued shares.
A79: Pre-SAFE planned ownership | B79: 1 | C79: =$D$31 -> 1 | D79: =C79-B79 -> 0 | E79: =IF(ABS(D79)<0.0000001,"PASS","REVIEW") -> PASS | F79: Normalized among founder, core team targets and ESOP.
A80: Post-SAFE planned ownership | B80: 1 | C80: =$C$48 -> 1 | D80: =C80-B80 -> 0 | E80: =IF(ABS(D80)<0.0000001,"PASS","REVIEW") -> PASS | F80: Founder + core team + ESOP + SAFE.
A81: SAFE tiers total | B81: 0.1 | C81: =$D$39 -> 0.1 | D81: =C81-B81 -> 0 | E81: =IF(ABS(D81)<0.0000001,"PASS","REVIEW") -> PASS | F81: Three proposed tiers.
A82: All checks compare formulas to the confirmed legal and planning controls; PASS does not convert a planning assumption into issued ownership.
A84: 8. OWNERSHIP CHART
A85: The chart below uses only the four owner groups in the Pro Forma Post-SAFE Ownership section (rows 44–47).

Sheet Hiring & Compensation Plan
A1: MONTHLY COMP SCHEDULE (Core-team)
A2: Core-team comps : Compensation follows three progressive stages: TEST, PRE-VALIDATION and VETTED. Timing and amounts remain subject to milestone achievement.
A4: NAME | B4: Profile | C4: Start Month | D4: Metric | E4: M1 | F4: M2 | G4: M3 | H4: M4 | I4: M5 | J4: M6 | K4: M7 | L4: M8 | M4: M9 | N4: M10 | O4: M11 | P4: M12 | Q4: M13 | R4: M14 | S4: M15 | T4: M16 | U4: M17 | V4: M18 | W4: TOTAL 12M | X4: TOTAL 18M | Z4: AVANTAGE JEI
A5: THMS | B5: Founder | C5: M1 | D5: Net mensuel | E5: 2000 | F5: 3000 | G5: 3000 | H5: 3000 | I5: 3000 | J5: 3000 | K5: 3000 | L5: 3000 | M5: 3000 | N5: 3000 | O5: 3000 | P5: 3000 | Q5: 3000 | R5: 3000 | S5: 3000 | T5: 3000 | U5: 3000 | V5: 3000 | W5: =SUM(E5:P5) -> 35000 | X5: =SUM(E5:V5) -> 53000 | Z5: an 1 -> an 2
A6: THMS | B6: Founder | C6: M1 | D6: Brut mensuel | E6: 2597.4 | F6: 3896.1 | G6: 3896.1 | H6: 3896.1 | I6: 3896.1 | J6: 3896.1 | K6: 3896.1 | L6: 3896.1 | M6: 3896.1 | N6: 3896.1 | O6: 3896.1 | P6: 3896.1 | Q6: 3896.1 | R6: 3896.1 | S6: 3896.1 | T6: 3896.1 | U6: 3896.1 | V6: 3896.1 | W6: =SUM(E6:P6) -> 45454.5 | X6: =SUM(E6:V6) -> 68831.1
A7: THMS | B7: Founder | C7: M1 | D7: Chargé normal | E7: 1090.91 | F7: 1636.36 | G7: 1636.36 | H7: 1636.36 | I7: 1636.36 | J7: 1636.36 | K7: 1636.36 | L7: 1636.36 | M7: 1636.36 | N7: 1636.36 | O7: 1636.36 | P7: 1636.36 | Q7: 1636.36 | R7: 1636.36 | S7: 1636.36 | T7: 1636.36 | U7: 1636.36 | V7: 1636.36 | W7: =SUM(E7:P7) -> 19090.87 | X7: =SUM(E7:V7) -> 28909.03
A8: THMS | B8: Founder | C8: M1 | D8: Chargé JEI | E8: 763.64 | F8: 1145.45 | G8: 1145.45 | H8: 1145.45 | I8: 1145.45 | J8: 1145.45 | K8: 1145.45 | L8: 1145.45 | M8: 1145.45 | N8: 1145.45 | O8: 1145.45 | P8: 1145.45 | Q8: 1145.45 | R8: 1145.45 | S8: 1145.45 | T8: 1145.45 | U8: 1145.45 | V8: 1145.45 | W8: =SUM(H8:P8) -> 10309.05 | X8: =SUM(H8:V8) -> 17181.75
A9: THMS | B9: Founder | C9: M1 | D9: Total mensuel | E9: 3361.04 | F9: 5041.56 | G9: 5041.56 | H9: 5041.56 | I9: 5041.56 | J9: 5041.56 | K9: 5041.56 | L9: 5041.56 | M9: 5041.56 | N9: 5041.56 | O9: 5041.56 | P9: 5041.56 | Q9: 5041.56 | R9: 5041.56 | S9: 5041.56 | T9: 5041.56 | U9: 5041.56 | V9: 5041.56 | W9: =SUM(E9:P9) -> 58818.2 | X9: =SUM(E9:V9) -> 89067.56 | Z9: =X7-X8 -> 11727.28
A10: JSPH | B10: AI/Robotics eng | C10: M2 | D10: Net mensuel | F10: 2000 | G10: 3000 | H10: 3000 | I10: 4000 | J10: 4000 | K10: 4000 | L10: 4000 | M10: 4000 | N10: 4000 | O10: 4000 | P10: 4000 | Q10: 4000 | R10: 4000 | S10: 4000 | T10: 4000 | U10: 4000 | V10: 4000 | W10: =SUM(E10:P10) -> 40000 | X10: =SUM(E10:V10) -> 64000 | Z10: an 1 -> an 2
A11: JSPH | B11: AI/Robotics eng | C11: M2 | D11: Brut mensuel | E11: 0 | F11: 2597.4 | G11: 2597.4 | H11: 3896.1 | I11: 3896.1 | J11: 5194.81 | K11: 5194.81 | L11: 5194.81 | M11: 5194.81 | N11: 5194.81 | O11: 5194.81 | P11: 5194.81 | Q11: 5194.81 | R11: 5194.81 | S11: 5194.81 | T11: 5194.81 | U11: 5194.81 | V11: 5194.81 | W11: =SUM(E11:P11) -> 49350.67 | X11: =SUM(E11:V11) -> 80519.53
A12: JSPH | B12: AI/Robotics eng | C12: M2 | D12: Chargé normal | E12: 0 | F12: 1090.91 | G12: 1090.91 | H12: 1636.36 | I12: 1636.36 | J12: 2181.82 | K12: 2181.82 | L12: 2181.82 | M12: 2181.82 | N12: 2181.82 | O12: 2181.82 | P12: 2181.82 | Q12: 2181.82 | R12: 2181.82 | S12: 2181.82 | T12: 2181.82 | U12: 2181.82 | V12: 2181.82 | W12: =SUM(E12:P12) -> 20727.28 | X12: =SUM(E12:V12) -> 33818.2
A13: JSPH | B13: AI/Robotics eng | C13: M2 | D13: Chargé JEI | E13: 0 | F13: 763.64 | G13: 763.64 | H13: 1145.45 | I13: 1145.45 | J13: 1527.27 | K13: 1527.27 | L13: 1527.27 | M13: 1527.27 | N13: 1527.27 | O13: 1527.27 | P13: 1527.27 | Q13: 1527.27 | R13: 1527.27 | S13: 1527.27 | T13: 1527.27 | U13: 1527.27 | V13: 1527.27 | W13: =SUM(E13:P13) -> 14509.07 | X13: =SUM(E13:V13) -> 23672.69
A14: JSPH | B14: AI/Robotics eng | C14: M2 | D14: Total mensuel | E14: 0 | F14: 3361.04 | G14: 3361.04 | H14: 5041.56 | I14: 5041.56 | J14: 6722.08 | K14: 6722.08 | L14: 6722.08 | M14: 6722.08 | N14: 6722.08 | O14: 6722.08 | P14: 6722.08 | Q14: 6722.08 | R14: 6722.08 | S14: 6722.08 | T14: 6722.08 | U14: 6722.08 | V14: 6722.08 | W14: =SUM(E14:P14) -> 63859.76 | X14: =SUM(E14:V14) -> 104192.24 | Z14: =X12-X13 -> 10145.51
A15: DALI | B15: Maths applied eng | C15: M2 | D15: Net mensuel | E15: 0 | F15: 1000 | G15: 1000 | H15: 2000 | I15: 2000 | J15: 2500 | K15: 2500 | L15: 2500 | M15: 2500 | N15: 2500 | O15: 2500 | P15: 2500 | Q15: 2500 | R15: 2500 | S15: 2500 | T15: 2500 | U15: 2500 | V15: 2500 | W15: =SUM(E15:P15) -> 23500 | X15: =SUM(E15:V15) -> 38500 | Z15: an 1 -> an 2
A16: DALI | B16: Maths applied eng | C16: M2 | D16: Brut mensuel | E16: 0 | F16: 0 | G16: 0 | H16: 2597.4 | I16: 2597.4 | J16: 3246.75 | K16: 3246.75 | L16: 3246.75 | M16: 3246.75 | N16: 3246.75 | O16: 3246.75 | P16: 3246.75 | Q16: 3246.75 | R16: 3246.75 | S16: 3246.75 | T16: 3246.75 | U16: 3246.75 | V16: 3246.75 | W16: =SUM(E16:P16) -> 27922.05 | X16: =SUM(E16:V16) -> 47402.55
A17: DALI | B17: Maths applied eng | C17: M2 | D17: Chargé normal | E17: 0 | F17: 0 | G17: 0 | H17: 1090.91 | I17: 1090.91 | J17: 1363.64 | K17: 1363.64 | L17: 1363.64 | M17: 1363.64 | N17: 1363.64 | O17: 1363.64 | P17: 1363.64 | Q17: 1363.64 | R17: 1363.64 | S17: 1363.64 | T17: 1363.64 | U17: 1363.64 | V17: 1363.64 | W17: =SUM(E17:P17) -> 11727.3 | X17: =SUM(E17:V17) -> 19909.14
A18: DALI | B18: Maths applied eng | C18: M2 | D18: Chargé JEI | E18: 0 | F18: 0 | G18: 0 | H18: 763.64 | I18: 763.64 | J18: 954.55 | K18: 954.55 | L18: 954.55 | M18: 954.55 | N18: 954.55 | O18: 954.55 | P18: 954.55 | Q18: 954.55 | R18: 954.55 | S18: 954.55 | T18: 954.55 | U18: 954.55 | V18: 954.55 | W18: =SUM(E18:P18) -> 8209.13 | X18: =SUM(E18:V18) -> 13936.43
A19: DALI | B19: Maths applied eng | C19: M2 | D19: Total mensuel | E19: 0 | F19: 1212 | G19: 1212 | H19: 3361.04 | I19: 3361.04 | J19: 4201.3 | K19: 4201.3 | L19: 4201.3 | M19: 4201.3 | N19: 4201.3 | O19: 4201.3 | P19: 4201.3 | Q19: 4201.3 | R19: 4201.3 | S19: 4201.3 | T19: 4201.3 | U19: 4201.3 | V19: 4201.3 | W19: =SUM(E19:P19) -> 38555.18 | X19: =SUM(E19:V19) -> 63762.98 | Z19: =X17-X18 -> 5972.71
A20: NADR | B20: Embedded Sys eng | C20: M5 | D20: Net mensuel | E20: 0 | F20: 0 | G20: 0 | H20: 0 | I20: 2000 | J20: 2500 | K20: 2500 | L20: 3000 | M20: 3000 | N20: 3000 | O20: 3000 | P20: 3000 | Q20: 3000 | R20: 3000 | S20: 3000 | T20: 3000 | U20: 3000 | V20: 3000 | W20: =SUM(E20:P20) -> 22000 | X20: =SUM(E20:V20) -> 40000 | Z20: an 1 -> an 2
A21: NADR | B21: Embedded Sys eng | C21: M5 | D21: Brut mensuel | E21: 0 | F21: 0 | G21: 0 | H21: 0 | I21: 2597.4 | J21: 3246.75 | K21: 3246.75 | L21: 3896.1 | M21: 3896.1 | N21: 3896.1 | O21: 3896.1 | P21: 3896.1 | Q21: 3896.1 | R21: 3896.1 | S21: 3896.1 | T21: 3896.1 | U21: 3896.1 | V21: 3896.1 | W21: =SUM(E21:P21) -> 28571.4 | X21: =SUM(E21:V21) -> 51948
A22: NADR | B22: Embedded Sys eng | C22: M5 | D22: Chargé normal | E22: 0 | F22: 0 | G22: 0 | H22: 0 | I22: 1090.91 | J22: 1363.64 | K22: 1363.64 | L22: 1636.36 | M22: 1636.36 | N22: 1636.36 | O22: 1636.36 | P22: 1636.36 | Q22: 1636.36 | R22: 1636.36 | S22: 1636.36 | T22: 1636.36 | U22: 1636.36 | V22: 1636.36 | W22: =SUM(E22:P22) -> 11999.99 | X22: =SUM(E22:V22) -> 21818.15
A23: NADR | B23: Embedded Sys eng | C23: M5 | D23: Chargé JEI | E23: 0 | F23: 0 | G23: 0 | H23: 0 | I23: 763.64 | J23: 954.55 | K23: 954.55 | L23: 1145.45 | M23: 1145.45 | N23: 1145.45 | O23: 1145.45 | P23: 1145.45 | Q23: 1145.45 | R23: 1145.45 | S23: 1145.45 | T23: 1145.45 | U23: 1145.45 | V23: 1145.45 | W23: =SUM(E23:P23) -> 8399.99 | X23: =SUM(E23:V23) -> 15272.69 | Z23: =X21-X22 -> 30129.85
A24: NADR | B24: Embedded Sys eng | C24: M5 | D24: Total mensuel | E24: 0 | F24: 0 | G24: 0 | H24: 0 | I24: 3361.04 | J24: 4201.3 | K24: 4201.3 | L24: 5041.56 | M24: 5041.56 | N24: 5041.56 | O24: 5041.56 | P24: 5041.56 | Q24: 5041.56 | R24: 5041.56 | S24: 5041.56 | T24: 5041.56 | U24: 5041.56 | V24: 5041.56 | W24: =SUM(E24:P24) -> 36971.44 | X24: =SUM(E24:V24) -> 67220.8
A25: MAXM | B25: Fractional CTO (900/j) | C25: M2 | D25: Total (2,5j / m) | F25: 2250 | H25: 2250 | J25: 2250 | M25: 2250 | Q25: 2250 | U25: 2250 | W25: =SUM(E25:P25) -> 9000 | X25: =SUM(E25:V25) -> 13500
D27: Total mensuel | E27: =E9+E14+E19+E24+E25 -> 3361.04 | F27: =F9+F14+F19+F24+F25 -> 11864.6 | G27: =G9+G14+G19+G24+G25 -> 9614.6 | H27: =H9+H14+H19+H24+H25 -> 15694.16 | I27: =I9+I14+I19+I24+I25 -> 16805.2 | J27: =J9+J14+J19+J24+J25 -> 22416.24 | K27: =K9+K14+K19+K24+K25 -> 20166.24 | L27: =L9+L14+L19+L24+L25 -> 21006.5 | ... V27: =V9+V14+V19+V24+V25 -> 21006.5 | W27: =SUM(E27:P27) -> 207204.58 | X27: =SUM(E27:V27) -> 337743.58 | Z27: =Z23+Z19+Z14+Z9 -> 57975.35
A28: Hiring/Comp Budget = | B28: 350000 | E28: =B28-E27 -> 346638.96 | F28: =E28-F27 -> 334774.36 | G28: =F28-G27 -> 325159.76 | H28: =G28-H27 -> 309465.6 | I28: =H28-I27 -> 292660.4 | J28: =I28-J27 -> 270244.16 | K28: =J28-K27 -> 250077.92 | L28: =K28-L27 -> 229071.42 | M28: =L28-M27 -> 205814.92 | ... V28: =U28-V27 -> 12256.42 | W28: =P28 -> 142795.42 | X28: =V28+Z27 -> 70231.77
W29: Y1 Remainder | X29: M18 Remainder
A30: VESTING SCHEDULE (Core-team)
A31: Core-team vesting : 7-year progressive vesting starting from each person’s start date, with early cliff/low initial allocation and heavier vesting in years 4–7. Illustrative only : subject to final board approval, individual role, and counsel review at grant time.
E33: Y1 (vested) | F33: Left to vest | G33: Y2 (vested) | H33: Left to vest | I33: Y3 (vested) | J33: Left to vest | K33: Y4 (vested) | L33: Left to vest | M33: Y5 (vested) | N33: Left to vest | O33: Y6 (vested) | P33: Left to vest | Q33: Y7 (vested) | R33: Left to vest
A34: THMS | B34: Founder Equity | D34: % vested per year | E34: 0.25 | F34: 0.75 | G34: 0.5 | H34: 0.5 | I34: 0.75 | J34: 0.25 | K34: 1 | L34: 0 | M34: 1 | N34: 0 | O34: 1 | P34: 0 | Q34: 1 | R34: 0
B35: 40% (4,000,000 shares) | D35: total shares | E35: 1000000 | F35: 3000000 | G35: 2000000 | H35: 2000000 | I35: 3000000 | J35: 1000000 | K35: 4000000 | L35: 0 | M35: 4000000 | N35: 0 | O35: 4000000 | P35: 0 | Q35: 4000000 | R35: 0
A36: JSPH | B36: AI/Robotics Equity | D36: % vested per year | E36: CLIFF | F36: 1 | G36: 0.05 | H36: 0.95 | I36: 0.1 | J36: 0.85 | K36: 0.15 | L36: 0.7 | M36: 0.2 | N36: 0.5 | O36: 0.25 | P36: 0.25 | Q36: 0.25 | R36: 0
B37: 15% (1,500,000 shares) | D37: total shares | E37: 0 | F37: 1500000 | G37: 75000 | H37: 1425000 | I37: 225000 | J37: 1275000 | K37: 450000 | L37: 1050000 | M37: 750000 | N37: 750000 | O37: 1125000 | P37: 375000 | Q37: 1500000 | R37: 0
A38: DALI | B38: Maths applied Equity | D38: % vested per year | E38: CLIFF | F38: 1 | G38: 0.05 | H38: 0.95 | I38: 0.1 | J38: 0.85 | K38: 0.15 | L38: 0.7 | M38: 0.2 | N38: 0.5 | O38: 0.25 | P38: 0.25 | Q38: 0.25 | R38: 0
B39: 5% (500,000 shares) | D39: total shares | E39: 0 | F39: 500000 | G39: 25000 | H39: 475000 | I39: 75000 | J39: 425000 | K39: 150000 | L39: 350000 | M39: 250000 | N39: 250000 | O39: 375000 | P39: 125000 | Q39: 500000 | R39: 0
A40: NADR | B40: Embedded Sys Equity | D40: % vested per year | E40: CLIFF | F40: 1 | G40: 0.05 | H40: 0.95 | I40: 0.1 | J40: 0.85 | K40: 0.15 | L40: 0.7 | M40: 0.2 | N40: 0.5 | O40: 0.25 | P40: 0.25 | Q40: 0.25 | R40: 0
B41: 10% (1,000,000 shares) | D41: total shares | E41: 0 | F41: 1000000 | G41: 50000 | H41: 950000 | I41: 150000 | J41: 850000 | K41: 300000 | L41: 700000 | M41: 500000 | N41: 500000 | O41: 750000 | P41: 250000 | Q41: 1000000 | R41: 0
A42: NEXT | B42: Key-hire AI/Robotics | D42: To be found
B43: 10% (1,000,000 shares) | D43: provisioned
B44: *: 40% core-team pool at Seed. (ESOP 10% & SAFE Investors 10%)
A47: EXECUTIVE SUMMARY | D47: EMPLOYEE COST ROLL-UP | L47: NOTES & METHODOLOGY — HIRING PLAN
A48: Metric | B48: Value | D48: Employee | E48: Role | F48: Start Month | G48: Monthly Gross Salary | H48: Employer Cost | I48: Annual Cost | J48: 18-Month Cost | L48: 1. “Start Month” indicates the first month of planned engagement or compensation, including initial test-period arrangements.
A49: Total Payroll (12 Months) | B49: =$W$6+$W$11+$W$16+$W$21 -> 151298.62 | D49: THMS | E49: Founder | F49: M1 | G49: =$V$6 -> 3896.1 | H49: =$V$9 -> 5041.56 | I49: =$W$9 -> 58818.2 | J49: =$X$9 -> 89067.56 | L49: 2. “Total Payroll” represents cumulative gross salaries. “Total Employer Cost” includes modeled employer charges and the fractional CTO expenditure.
A50: Total Payroll (18 Months) | B50: =$X$6+$X$11+$X$16+$X$21 -> 248701.18 | D50: JSPH | E50: AI/Robotics eng | F50: M2 | G50: =$V$11 -> 5194.81 | H50: =$V$14 -> 6722.08 | I50: =$W$14 -> 63859.76 | J50: =$X$14 -> 104192.24 | L50: 3. Employer costs use the JEI-adjusted assumptions shown in the detailed schedule. Standard employer charges are retained for comparison and transparency.
A51: Average Monthly Payroll | B51: =B50/18 -> 13816.732 | D51: DALI | E51: Maths applied eng | F51: M2 | G51: =$V$16 -> 3246.75 | H51: =$V$19 -> 4201.3 | I51: =$W$19 -> 38555.18 | J51: =$X$19 -> 63762.98 | L51: 4. “Annual Cost” in the employee roll-up represents the actual first 12 months of the hiring schedule, not a normalized annual run rate.
A52: Average Team Size | B52: =((19-VALUE(SUBSTITUTE($C$5,"M","")))+(19-VALUE(SUBSTITUTE($C$10,"M","")))+(19-VALUE(SUBSTITUTE($C$15,"M","")))+(19-VALUE(SUBSTITUTE($C$20,"M","")))+(19-VALUE(SUBSTITUTE($C$25,"M",""))))/18 -> 4.6111111 | D52: NADR | E52: Embedded Sys eng | F52: M5 | G52: =$V$21 -> 3896.1 | H52: =$V$24 -> 5041.56 | I52: =$W$24 -> 36971.44 | J52: =$X$24 -> 67220.8 | L52: 5. Average team size is calculated from each contributor’s Start Month and includes the fractional CTO as an active contributor.
A53: Total Employer Cost (18 Months) | B53: =$X$27 -> 337743.58 | D53: MAXM | E53: Fractional CTO (900/j) | F53: M2 | H53: =AVERAGEIF($E$25:$V$25,">0") -> 2250 | I53: =$W$25 -> 9000 | J53: =$X$25 -> 13500 | L53: 6. This schedule covers compensation-related expenditure only. Travel, accommodation, meals, recruitment costs and other operating expenses should be budgeted separately in the future financial model.

Sheet MVP & lab hardware BOM
A1: BILL OF MATERIALS : MVP & LAB
A3: CATEGORY | B3: ITEM | C3: Qty | D3: M1 | E3: M2 | F3: M3 | G3: M4 | H3: M5 | I3: M6 | J3: M7 | K3: M8 | L3: M9 | M3: M10 | N3: M11 | O3: M12 | P3: M13 | Q3: M14 | R3: M15 | S3: M16 | T3: M17 | U3: M18 | V3: TOTAL 12M | W3: TOTAL 18M | X3: COST TYPE | Y3: Unit Cost | Z3: Grade | AA3: Pricing Source | AB3: Purchase Month | AC3: Technical Milestone | AD3: Technical Purpose
A4: Capture Hardware
A5: Capture Hardware | B5: Xsens MVN Awinda full system | C5: 1 | D5: 7800 | V5: =SUM(D5:O5) -> 7800 | W5: =SUM(D5:U5) -> 7800 | X5: CapEx | Y5: 7800 | Z5: A | AA5: Vendor / market pricing | AB5: Month 1 | AC5: Capture stack deployment | AD5: Full-body IMMU suit for operator kinematics, posture and balance capture
A6: Capture Hardware | B6: Delsys Trigno Avanti Starter Kit | C6: 1 | D6: 5300 | V6: =SUM(D6:O6) -> 5300 | W6: =SUM(D6:U6) -> 5300 | X6: CapEx | Y6: 5300 | Z6: A | AA6: Vendor / market pricing | AB6: Month 1 | AC6: Biomechanics sensing setup | AD6: Wireless sEMG for muscle activation and torque proxy estimation
A7: Capture Hardware | B7: BNC sync cable | C7: 1 | D7: 20 | V7: =SUM(D7:O7) -> 20 | W7: =SUM(D7:U7) -> 20 | X7: CapEx | Y7: 20 | Z7: A | AA7: Commodity accessory pricing | AB7: Month 1 | AC7: Sensor synchronization | AD7: Hardware trigger alignment between Xsens and Delsys
A8: Capture Hardware | B8: MANUS Quantum Metagloves | C8: 1 | D8: 4999 | V8: =SUM(D8:O8) -> 4999 | W8: =SUM(D8:U8) -> 4999 | X8: CapEx | Y8: 4999 | Z8: B | AA8: Current reseller / market pricing | AB8: Month 1 | AC8: Hand tracking setup | AD8: Hand kinematics for manipulation, teleoperation and finger pose capture
A9: Capture Hardware | B9: OSMO tactile glove custom build | C9: 1 | D9: 3590 | V9: =SUM(D9:O9) -> 3590 | W9: =SUM(D9:U9) -> 3590 | X9: CapEx | Y9: 3590 | Z9: C | AA9: Engineering build estimate (materials ~1.090€ + labour 2.500€) | AB9: Month 1 | AC9: Tactile sensing prototype | AD9: Full palmar and finger contact, normal + shear force mapping
A10: Capture Hardware | B10: Intel RealSense D435i | C10: 1 | D10: 320 | V10: =SUM(D10:O10) -> 320 | W10: =SUM(D10:U10) -> 320 | X10: CapEx | Y10: 320 | Z10: B | AA10: Current street price (roboticscenter.ai depth camera survey) - Intel wound down RealSense unit, supply continuity risk | AB10: Month 1 | AC10: RGB-D scene capture | AD10: Close-range RGB-D capture of manipulation scenes
A11: Capture Hardware | B11: RoboSense RS-Helios-16P LiDAR | C11: 1 | G11: 1500 | V11: =SUM(D11:O11) -> 1500 | W11: =SUM(D11:U11) -> 1500 | X11: CapEx | Y11: 1500 | Z11: C | AA11: Reseller estimate - confirm with EU quote before data room | AB11: Month 4 | AC11: Room-scale spatial mapping | AD11: Room-scale 3D spatial mapping and larger workcell geometry
A12: Capture Hardware | B12: Logitech Brio 4K | C12: 1 | D12: 170 | V12: =SUM(D12:O12) -> 170 | W12: =SUM(D12:U12) -> 170 | X12: CapEx | Y12: 170 | Z12: A | AA12: Logitech FR store list price 169,99EUR | AB12: Month 1 | AC12: Visual annotation setup | AD12: Frontal RGB stream for annotation and VLM input
A13: Capture Hardware | B13: Rode NT-USB Mini | C13: 1 | D13: 100 | V13: =SUM(D13:O13) -> 100 | W13: =SUM(D13:U13) -> 100 | X13: CapEx | Y13: 100 | Z13: A | AA13: Public retail pricing | AB13: Month 1 | AC13: Voice annotation setup | AD13: Voice-to-text annotation during capture sessions
A14: Capture Hardware | B14: CVAT subscription (annual) | C14: 1 | D14: 290 | O14: 290 | V14: =SUM(D14:O14) -> 580 | W14: =SUM(D14:U14) -> 580 | X14: OpEx | Y14: 290 | Z14: B | AA14: Subscription pricing | AB14: Month 1 | AC14: Annotation workflow launch | AD14: Manual and assisted annotation interface
A15: Capture Hardware | B15: Network switch, cabling, UPS, accessories | C15: 1 | D15: 850 | V15: =SUM(D15:O15) -> 850 | W15: =SUM(D15:U15) -> 850 | X15: CapEx | Y15: 850 | Z15: B | AA15: System-integrator estimate | AB15: Month 1 | AC15: Lab infrastructure setup | AD15: Lab networking, power conditioning and cable management
A16: Capture Hardware | B16: Spare sensors, spare cables, calibration consumables | C16: 1 | D16: 650 | V16: =SUM(D16:O16) -> 650 | W16: =SUM(D16:U16) -> 650 | X16: OpEx | Y16: 650 | Z16: C | AA16: Engineering contingency | AB16: Month 1 | AC16: Capture continuity readiness | AD16: Reduce downtime and avoid blocked capture sessions
A17: Capture Hardware | B17: Multi-sensor calibration rig / jig | C17: 1 | D17: 1500 | V17: =SUM(D17:O17) -> 1500 | W17: =SUM(D17:U17) -> 1500 | X17: CapEx | Y17: 1500 | Z17: C | AA17: Engineering estimate | AB17: Month 1 | AC17: Multi-sensor calibration | AD17: Cross-sensor spatial and temporal alignment across Xsens, Delsys, MANUS, OSMO and RGB-D
B18: Capture Hardware — SUBTOTAL | D18: =SUM(D5:D17) -> 25589 | E18: =SUM(E5:E17) -> 0 | F18: =SUM(F5:F17) -> 0 | G18: =SUM(G5:G17) -> 1500 | H18: =SUM(H5:H17) -> 0 | I18: =SUM(I5:I17) -> 0 | J18: =SUM(J5:J17) -> 0 | K18: =SUM(K5:K17) -> 0 | ... W18: =SUM(W5:W17) -> 27379
A20: Shared Dataset Storage
A21: Shared Dataset Storage | B21: Synology NAS or equivalent | C21: 1 | D21: 900 | V21: =SUM(D21:O21) -> 900 | W21: =SUM(D21:U21) -> 900 | X21: CapEx | Y21: 900 | Z21: B | AA21: Market pricing | AB21: Month 1 | AC21: Dataset storage deployment | AD21: Shared proprietary dataset storage and collaboration
A22: Shared Dataset Storage | B22: RAID drives / redundancy | C22: 1 | D22: 300 | V22: =SUM(D22:O22) -> 300 | W22: =SUM(D22:U22) -> 300 | X22: CapEx | Y22: 300 | Z22: B | AA22: Market pricing | AB22: Month 1 | AC22: Redundancy & backup | AD22: Redundant storage for captured datasets and backups
A23: Shared Dataset Storage | B23: NAS setup / accessories | C23: 1 | D23: 100 | V23: =SUM(D23:O23) -> 100 | W23: =SUM(D23:U23) -> 100 | X23: CapEx | Y23: 100 | Z23: C | AA23: Engineering estimate | AB23: Month 1 | AC23: Storage commissioning | AD23: Cabling, trays and deployment accessories
B24: Shared Dataset Storage — SUBTOTAL | D24: =SUM(D21:D23) -> 1300 | E24: =SUM(E21:E23) -> 0 | F24: =SUM(F21:F23) -> 0 | G24: =SUM(G21:G23) -> 0 | H24: =SUM(H21:H23) -> 0 | I24: =SUM(I21:I23) -> 0 | J24: =SUM(J21:J23) -> 0 | K24: =SUM(K21:K23) -> 0 | ... W24: =SUM(W21:W23) -> 1300
A26: Development Compute
A27: Development Compute | B27: GPU: RTX 5090 class | C27: 1 | D27: 4000 | V27: =SUM(D27:O27) -> 4000 | W27: =SUM(D27:U27) -> 4000 | X27: CapEx | Y27: 4000 | Z27: B | AA27: French retail 3.700-5.500EUR (MSRP 2.349EUR not achievable) | AB27: Month 1 | AC27: Local AI workstation deployment | AD27: Local VLM inference, moderate experimentation, fast iteration
A28: Development Compute | B28: CPU: Ryzen 9 9950X / i9 class | C28: 1 | D28: 800 | V28: =SUM(D28:O28) -> 800 | W28: =SUM(D28:U28) -> 800 | X28: CapEx | Y28: 800 | Z28: B | AA28: Market estimate | AB28: Month 1 | AC28: Local AI workstation deployment | AD28: Dataset preprocessing, annotation orchestration, robotics development
A29: Development Compute | B29: Motherboard: X870E / Z890 class | C29: 1 | D29: 450 | V29: =SUM(D29:O29) -> 450 | W29: =SUM(D29:U29) -> 450 | X29: CapEx | Y29: 450 | Z29: B | AA29: Market estimate | AB29: Month 1 | AC29: Local AI workstation deployment | AD29: PCIe lanes, storage expansion, workstation reliability
A30: Development Compute | B30: RAM: 192 GB DDR5 | C30: 1 | D30: 1250 | V30: =SUM(D30:O30) -> 1250 | W30: =SUM(D30:U30) -> 1250 | X30: CapEx | Y30: 1250 | Z30: B | AA30: 2026 DDR5 shortage: 32GB kits 385-460EUR | AB30: Month 1 | AC30: Local AI workstation deployment | AD30: Large preprocessing jobs, local experiments, multi-process pipelines
A31: Development Compute | B31: NVMe SSD: 2 TB OS / workspace | C31: 1 | D31: 180 | V31: =SUM(D31:O31) -> 180 | W31: =SUM(D31:U31) -> 180 | X31: CapEx | Y31: 180 | Z31: A | AA31: Commodity pricing | AB31: Month 1 | AC31: Local AI workstation deployment | AD31: System drive and application workspace
A32: Development Compute | B32: NVMe SSD: 4 TB scratch / dataset staging | C32: 2 | D32: 700 | V32: =SUM(D32:O32) -> 700 | W32: =SUM(D32:U32) -> 700 | X32: CapEx | Y32: 350 | Z32: A | AA32: Commodity pricing | AB32: Month 1 | AC32: Local AI workstation deployment | AD32: Fast local scratch, cached models, staged datasets
A33: Development Compute | B33: HDD / SSD backup pool | C33: 1 | D33: 300 | V33: =SUM(D33:O33) -> 300 | W33: =SUM(D33:U33) -> 300 | X33: CapEx | Y33: 300 | Z33: B | AA33: Market estimate | AB33: Month 1 | AC33: Local AI workstation deployment | AD33: Secondary local backup and snapshot retention
A34: Development Compute | B34: PSU: 1200W Platinum | C34: 1 | D34: 300 | V34: =SUM(D34:O34) -> 300 | W34: =SUM(D34:U34) -> 300 | X34: CapEx | Y34: 300 | Z34: B | AA34: Market estimate | AB34: Month 1 | AC34: Local AI workstation deployment | AD34: Stable power delivery for high-end GPU workloads
A35: Development Compute | B35: Cooling: high-end air or 360 mm AIO | C35: 1 | D35: 250 | V35: =SUM(D35:O35) -> 250 | W35: =SUM(D35:U35) -> 250 | X35: CapEx | Y35: 250 | Z35: B | AA35: Market estimate | AB35: Month 1 | AC35: Local AI workstation deployment | AD35: Thermal headroom for sustained inference and preprocessing
A36: Development Compute | B36: Case / assembly / cabling | C36: 1 | D36: 250 | V36: =SUM(D36:O36) -> 250 | W36: =SUM(D36:U36) -> 250 | X36: CapEx | Y36: 250 | Z36: B | AA36: Market estimate | AB36: Month 1 | AC36: Local AI workstation deployment | AD36: Build integration and serviceability
A37: Development Compute | B37: UPS for workstation, 1500 VA line-interactive | C37: 1 | D37: 550 | V37: =SUM(D37:O37) -> 550 | W37: =SUM(D37:U37) -> 550 | X37: CapEx | Y37: 550 | Z37: B | AA37: Re-specified for 575W GPU + 170W CPU sustained load | AB37: Month 1 | AC37: Local AI workstation deployment | AD37: Prevent data loss and corruption during power events
A38: Development Compute | B38: Dual 27-inch monitors | C38: 2 | D38: 600 | V38: =SUM(D38:O38) -> 600 | W38: =SUM(D38:U38) -> 600 | X38: CapEx | Y38: 300 | Z38: B | AA38: Market estimate | AB38: Month 1 | AC38: Local AI workstation deployment | AD38: Annotation, debugging and simultaneous pipeline monitoring
A39: Development Compute | B39: Keyboard, mouse, webcam, headset, peripherals | C39: 1 | D39: 250 | V39: =SUM(D39:O39) -> 250 | W39: =SUM(D39:U39) -> 250 | X39: CapEx | Y39: 250 | Z39: A | AA39: Commodity pricing | AB39: Month 1 | AC39: Local AI workstation deployment | AD39: Daily development and annotation ergonomics
B40: Development Compute — SUBTOTAL | D40: =SUM(D27:D39) -> 9880 | E40: =SUM(E27:E39) -> 0 | F40: =SUM(F27:F39) -> 0 | G40: =SUM(G27:G39) -> 0 | H40: =SUM(H27:H39) -> 0 | I40: =SUM(I27:I39) -> 0 | J40: =SUM(J27:J39) -> 0 | K40: =SUM(K27:K39) -> 0 | ... W40: =SUM(W27:W39) -> 9880
A42: Embedded AI Compute
A43: Embedded AI Compute | B43: Jetson AGX Orin Developer Kit | C43: 1 | G43: 3499 | V43: =SUM(D43:O43) -> 3499 | W43: =SUM(D43:U43) -> 3499 | X43: CapEx | Y43: 3499 | Z43: A | AA43: Vendor / public pricing | AB43: Month 4 | AC43: Runtime validation (Orin) | AD43: Embedded deployment, runtime validation, ROS2 integration
A44: Embedded AI Compute | B44: Orin: NVMe SSD for edge logging | C44: 1 | G44: 150 | V44: =SUM(D44:O44) -> 150 | W44: =SUM(D44:U44) -> 150 | X44: CapEx | Y44: 150 | Z44: A | AA44: Commodity pricing | AB44: Month 4 | AC44: Runtime validation (Orin) | AD44: Local buffering of sensor logs and TrustVault artefacts
A45: Embedded AI Compute | B45: Orin: rugged network switch / router | C45: 1 | G45: 250 | V45: =SUM(D45:O45) -> 250 | W45: =SUM(D45:U45) -> 250 | X45: CapEx | Y45: 250 | Z45: B | AA45: Market estimate | AB45: Month 4 | AC45: Runtime validation (Orin) | AD45: Field-test networking and ROS2 data routing
A46: Embedded AI Compute | B46: Orin: power delivery / spare PSU | C46: 1 | G46: 120 | V46: =SUM(D46:O46) -> 120 | W46: =SUM(D46:U46) -> 120 | X46: CapEx | Y46: 120 | Z46: B | AA46: Market estimate | AB46: Month 4 | AC46: Runtime validation (Orin) | AD46: Stable power during demos and field tests
A47: Embedded AI Compute | B47: Orin: housings, cables, adapters | C47: 1 | G47: 220 | V47: =SUM(D47:O47) -> 220 | W47: =SUM(D47:U47) -> 220 | X47: CapEx | Y47: 220 | Z47: B | AA47: Engineering estimate | AB47: Month 4 | AC47: Runtime validation (Orin) | AD47: Mechanical integration and deployment readiness
A48: Embedded AI Compute | B48: Partner robot integration kit | C48: 1 | G48: 1000 | V48: =SUM(D48:O48) -> 1000 | W48: =SUM(D48:U48) -> 1000 | X48: CapEx | Y48: 1000 | Z48: C | AA48: Engineering estimate | AB48: Month 4 | AC48: Partner robot integration | AD48: Jetson mounting brackets, power tap, cable harness and connector adapters for partner-supplied humanoid platforms
A49: Embedded AI Compute | B49: Jetson AGX Thor Developer Kit | C49: 1 | P49: 5499 | V49: =SUM(D49:O49) -> 0 | W49: =SUM(D49:U49) -> 5499 | X49: CapEx | Y49: 5499 | Z49: A | AA49: Vendor / public pricing | AB49: Month 12-15 (modelled M13) | AC49: On-device multimodal reasoning | AD49: On-device multimodal reasoning, local VLM/VLA inference, TrustVault runtime
A50: Embedded AI Compute | B50: Thor: NVMe SSD for local model storage | C50: 1 | P50: 250 | V50: =SUM(D50:O50) -> 0 | W50: =SUM(D50:U50) -> 250 | X50: CapEx | Y50: 250 | Z50: A | AA50: Commodity pricing | AB50: Month 12-15 (modelled M13) | AC50: On-device multimodal reasoning | AD50: Store local reasoning models, embeddings and cached context
A51: Embedded AI Compute | B51: Thor: rugged network switch / router | C51: 1 | P51: 250 | V51: =SUM(D51:O51) -> 0 | W51: =SUM(D51:U51) -> 250 | X51: CapEx | Y51: 250 | Z51: B | AA51: Market estimate | AB51: Month 12-15 (modelled M13) | AC51: On-device multimodal reasoning | AD51: Field connectivity for offline-first deployments
A52: Embedded AI Compute | B52: Thor: power delivery / enclosure / adapters | C52: 1 | P52: 300 | V52: =SUM(D52:O52) -> 0 | W52: =SUM(D52:U52) -> 300 | X52: CapEx | Y52: 300 | Z52: B | AA52: Engineering estimate | AB52: Month 12-15 (modelled M13) | AC52: On-device multimodal reasoning | AD52: Power and integration for robot-mounted deployment
B53: Embedded AI Compute — SUBTOTAL | D53: =SUM(D43:D52) -> 0 | E53: =SUM(E43:E52) -> 0 | F53: =SUM(F43:F52) -> 0 | G53: =SUM(G43:G52) -> 5239 | H53: =SUM(H43:H52) -> 0 | I53: =SUM(I43:I52) -> 0 | J53: =SUM(J43:J52) -> 0 | K53: =SUM(K43:K52) -> 0 | ... W53: =SUM(W43:W52) -> 11538
A55: Lab Operations & Risk
A56: Lab Operations & Risk | B56: Lab safety equipment (E-stop, barriers, PPE) | C56: 1 | G56: 800 | V56: =SUM(D56:O56) -> 800 | W56: =SUM(D56:U56) -> 800 | X56: CapEx | Y56: 800 | Z56: C | AA56: Engineering estimate | AB56: Month 4 | AC56: Lab safety readiness | AD56: Operator safety obligations once powered actuation enters the lab
A57: Lab Operations & Risk | B57: Equipment insurance (18 months) | C57: 18 | D57: 50 | E57: 50 | F57: 50 | G57: 50 | H57: 50 | I57: 50 | J57: 50 | K57: 50 | L57: 50 | M57: 50 | N57: 50 | O57: 50 | P57: 50 | Q57: 50 | R57: 50 | S57: 50 | T57: 50 | U57: 50 | V57: =SUM(D57:O57) -> 600 | W57: =SUM(D57:U57) -> 900 | X57: OpEx | Y57: 50 | Z57: C | AA57: Insurance estimate on ~52k EUR of assets | AB57: Ongoing (M1-M18) | AC57: Ongoing asset protection | AD57: Cover theft, damage and loss on Xsens, Delsys, MANUS and compute assets
A58: Lab Operations & Risk | B58: Warranty / extended support contracts | C58: 1 | D58: 500 | V58: =SUM(D58:O58) -> 500 | W58: =SUM(D58:U58) -> 500 | X58: OpEx | Y58: 500 | Z58: C | AA58: Vendor support estimate | AB58: Month 1 | AC58: Hardware support readiness | AD58: Coverage on Jetson, GPU and NAS hardware
A59: Lab Operations & Risk | B59: Hardware contingency reserve (5% of physical assets) | C59: 1 | D59: 144.44 | E59: 144.44 | F59: 144.44 | G59: 144.44 | H59: 144.44 | I59: 144.44 | J59: 144.44 | K59: 144.44 | L59: 144.44 | M59: 144.44 | N59: 144.44 | O59: 144.44 | P59: 144.44 | Q59: 144.44 | R59: 144.44 | S59: 144.44 | T59: 144.44 | U59: 144.52 | V59: =SUM(D59:O59) -> 1733.28 | W59: =SUM(D59:U59) -> 2600 | X59: OpEx | Y59: 2600 | Z59: C | AA59: 5% of pre-contingency physical assets (52.007,00EUR) | AB59: Reserve, drawn M1-M18 | AC59: Risk reserve | AD59: Failure, calibration drift, shipping damage, single-unit replacement
B60: Lab Operations & Risk — SUBTOTAL | D60: =SUM(D56:D59) -> 694.44 | E60: =SUM(E56:E59) -> 194.44 | F60: =SUM(F56:F59) -> 194.44 | G60: =SUM(G56:G59) -> 994.44 | H60: =SUM(H56:H59) -> 194.44 | I60: =SUM(I56:I59) -> 194.44 | J60: =SUM(J56:J59) -> 194.44 | K60: =SUM(K56:K59) -> 194.44 | ... W60: =SUM(W56:W59) -> 4800
A62: Cloud Compute (OpEx)
A63: Cloud Compute (OpEx) | B63: Inference / evaluation (~40 GPU-hr/month, low-cost GPUs) | D63: 38.71 | E63: 38.71 | F63: 51.61 | G63: 51.61 | H63: 64.52 | I63: 64.52 | J63: 64.52 | K63: 64.52 | L63: 64.52 | M63: 77.42 | N63: 77.42 | O63: 77.42 | P63: 77.42 | Q63: 77.42 | R63: 77.42 | S63: 77.42 | T63: 77.42 | U63: 77.4 | V63: =SUM(D63:O63) -> 735.5 | W63: =SUM(D63:U63) -> 1200 | X63: OpEx | Z63: B | AA63: RunPod / Vast.ai class pricing | AB63: Ongoing (M1-M18) | AC63: Continuous inference & evaluation | AD63: Burst inference and model evaluation runs
A64: Cloud Compute (OpEx) | B64: Experimentation (~80 GPU-hr/month, mid-tier GPUs) | E64: 93.57 | F64: 112.28 | G64: 130.99 | H64: 149.71 | I64: 168.42 | J64: 187.13 | K64: 187.13 | L64: 187.13 | M64: 205.85 | N64: 205.85 | O64: 224.56 | P64: 224.56 | Q64: 224.56 | R64: 224.56 | S64: 224.56 | T64: 224.56 | U64: 224.58 | V64: =SUM(D64:O64) -> 1852.62 | W64: =SUM(D64:U64) -> 3200 | X64: OpEx | Z64: B | AA64: Lambda Labs / RunPod market references | AB64: Ongoing (M1-M18) | AC64: Experimentation ramp | AD64: Architecture and pipeline experimentation, benchmarking
A65: Cloud Compute (OpEx) | B65: Fine-tuning (~140 GPU-hr/month in selected bursts) | G65: 243.04 | H65: 303.8 | I65: 425.32 | J65: 486.08 | K65: 607.59 | L65: 607.59 | M65: 668.35 | N65: 668.35 | O65: 729.11 | P65: 729.11 | Q65: 789.87 | R65: 789.87 | S65: 850.63 | T65: 850.63 | U65: 850.66 | V65: =SUM(D65:O65) -> 4739.23 | W65: =SUM(D65:U65) -> 9600 | X65: OpEx | Z65: B | AA65: A100 / H100 burst pricing | AB65: Ongoing (M1-M18) | AC65: Fine-tuning ramp | AD65: Policy and VLM fine-tuning on captured datasets
A66: Cloud Compute (OpEx) | B66: Larger training jobs (event-driven, ~1.500 GPU-hr @ ~7,00EUR/hr) | K66: 2625 | N66: 2625 | Q66: 2625 | T66: 2625 | V66: =SUM(D66:O66) -> 5250 | W66: =SUM(D66:U66) -> 10500 | X66: OpEx | Z66: C | AA66: Hyperscaler H100 tier ~7,00EUR/GPU-hr (AWS 6,88-7,57 USD) | AB66: Ongoing (M1-M18) | AC66: Model iteration milestones | AD66: Milestone training runs clustered around model iterations
A67: Cloud Compute (OpEx) | B67: Storage, snapshots, transfer, misc. services | D67: 64.43 | E67: 77.32 | F67: 90.21 | G67: 103.09 | H67: 115.98 | I67: 128.87 | J67: 128.87 | K67: 141.75 | L67: 141.75 | M67: 154.64 | N67: 154.64 | O67: 154.64 | P67: 167.53 | Q67: 167.53 | R67: 167.53 | S67: 180.41 | T67: 180.41 | U67: 180.4 | V67: =SUM(D67:O67) -> 1456.19 | W67: =SUM(D67:U67) -> 2500 | X67: OpEx | Z67: C | AA67: Cloud service usage projection | AB67: Ongoing (M1-M18) | AC67: Data operations | AD67: Dataset storage, snapshots, egress and ancillary services
B68: Cloud Compute (OpEx) — SUBTOTAL | D68: =SUM(D63:D67) -> 103.14 | E68: =SUM(E63:E67) -> 209.6 | F68: =SUM(F63:F67) -> 254.1 | G68: =SUM(G63:G67) -> 528.73 | H68: =SUM(H63:H67) -> 634.01 | I68: =SUM(I63:I67) -> 787.13 | J68: =SUM(J63:J67) -> 866.6 | K68: =SUM(K63:K67) -> 3625.99 | ... W68: =SUM(W63:W67) -> 27000
B70: TOTAL INFRASTRUCTURE — MVP & LAB HARDWARE | D70: =D18+D24+D40+D53+D60+D68 -> 37566.58 | E70: =E18+E24+E40+E53+E60+E68 -> 404.04 | F70: =F18+F24+F40+F53+F60+F68 -> 448.54 | G70: =G18+G24+G40+G53+G60+G68 -> 8262.17 | H70: =H18+H24+H40+H53+H60+H68 -> 828.45 | I70: =I18+I24+I40+I53+I60+I68 -> 981.57 | J70: =J18+J24+J40+J53+J60+J68 -> 1061.04 | K70: =K18+K24+K40+K53+K60+K68 -> 3820.43 | ... W70: =W18+W24+W40+W53+W60+W68 -> 81897
B73: EXECUTIVE SUMMARY
B74: Category | C74: Total 12M | D74: Total 18M | E74: % of 18M budget | F74: Purchase phase | I74: Notes & methodology - BOM v3 (Bill of Materials)
B75: Capture Hardware | C75: =V18 -> 27379 | D75: =W18 -> 27379 | E75: =W18/$W$70 -> 0.33431017 | F75: Month 1 | I75: 1. All prices are HT (excluding VAT). Column structure mirrors the 'Team Compensation Timeline' tab: D:U = M1..M18, V = TOTAL 12M (=SUM(D:O)), W = TOTAL 18M (=SUM(D:U)). All totals are live formulas.
B76: Shared Dataset Storage | C76: =V24 -> 1300 | D76: =W24 -> 1300 | E76: =W24/$W$70 -> 0.015873597 | F76: Month 1 | I76: 2. CapEx items are booked in full in their purchase month (cash-out basis), not depreciated. French practice allows 3-year straight-line depreciation for computer equipment above 500,00EUR HT unit value (compte 2183); items below expense immediately (compte 6063).
B77: Development Compute | C77: =V40 -> 9880 | D77: =W40 -> 9880 | E77: =W40/$W$70 -> 0.12063934 | F77: Month 1 | I77: 3. Jetson AGX Thor is booked in M13 as the mid-point of the documented Month 12-15 window. It therefore falls outside TOTAL 12M by design - this is the disciplined-capital-allocation story, not an omission.
B78: Embedded AI Compute | C78: =V53 -> 5239 | D78: =W53 -> 11538 | E78: =W53/$W$70 -> 0.14088428 | F78: Month 4 (Orin) / M12-15 (Thor) | I78: 4. Cloud compute is spread as a ramp, not flat: usage grows as datasets and model iterations grow. Larger training jobs are booked as four event-driven bursts (M8, M11, M14, M17).
B79: Lab Operations & Risk | C79: =V60 -> 3633.28 | D79: =W60 -> 4800 | E79: =W60/$W$70 -> 0.058610205 | F79: M1 / M4 / ongoing reserve | I79: 5. Confidence grades: A = official vendor pricing or quotation; B = current market pricing from reputable distributors or integrators; C = engineering estimate or projected pricing.
B80: Cloud Compute (OpEx) | C80: =V68 -> 14033.54 | D80: =W68 -> 27000 | E80: =W68/$W$70 -> 0.32968241 | F80: Ongoing M1-M18
B81: GRAND TOTAL | C81: =SUM(C75:C80) -> 61464.82 | D81: =SUM(D75:D80) -> 81897 | E81: 1 | I81: CHANGES APPLIED FROM BOM v2 (total 69.727,00EUR -> 78.982,00EUR, +9.255,00EUR):
I82: Arithmetic corrections (+990,00EUR): Capture subtotal 24.009 -> 23.999 (line items never summed to 24.009); Development Compute 6.880 -> 7.880 (2 x 4TB NVMe counted once); KPI Physical Assets 46.727 -> reconciled (v2 contradicted its own category sums and printed three different grand totals).
B83: INFRASTRUCTURE KPIs | I83: Market re-pricing (+2.090,00EUR): RTX 5090 2.800 -> 4.000 (French retail 3.700-5.500, MSRP 2.349 not achievable); 192GB DDR5 650 -> 1.250 (2026 memory shortage); RealSense D435i 200 -> 320 (street price, plus disclosed Intel discontinuation risk); Logitech Brio 200 -> 170 (Logitech FR list); workstation UPS 350 -> 550 (1500VA class for 575W GPU + 170W CPU).
B84: Physical assets (CapEx, HT, 18M) | D84: =W18+W24+W40+W53+W60 -> 54897 | I84: New scope: multi-sensor calibration rig 1.500 (M1); RoboSense RS-Helios-16P room-scale LiDAR 1.500 reinstated (M4); partner robot integration kit 1.000 (M4); Lab Operations & Risk category (safety equipment, 18-month equipment insurance, warranty/support, 5% hardware contingency reserve).
B85: Recurring cloud compute (OpEx, 18M) | D85: =W68 -> 27000 | I85: Cloud fix (0,00EUR): 'Larger training jobs' GPU-hour assumption corrected from 240 to 1.500 hours so the implied rate is 7,00EUR/GPU-hr instead of 43,75EUR/GPU-hr, which exceeded every real market rate. Budget unchanged.
B86: Total infrastructure investment (HT, 18M) | D86: =W70 -> 81897 | I86: Verified unchanged: Jetson Orin 3.499 and Thor 5.499 both match NVIDIA post-July-2026 MSRPs; MANUS Quantum 4.999 exact match to EU reseller; Xsens, Delsys, Rode, CVAT, NVMe, PSU, monitors all within market range.
B87: Total infrastructure investment (HT, 12M) | D87: =V70 -> 61464.82
B88: Insurance premiums (VAT-exempt in France) | D88: 900 | I88: VAT: prices are HT. 20% French VAT on the equipment base (physical assets less VAT-exempt insurance premiums) is a cash-timing item, recoverable in full via CA3 box 20 under regime reel for exclusively professional use. Requires SASU/EURL/SAS - micro-enterprise status does not permit recovery. Cloud compute from non-EU providers falls under reverse charge (autoliquidation), no net cash outflow.
B89: VAT-bearing equipment base (HT) | D89: =D84-D88 -> 53997 | I89: CIR: the 30% credit applies to the annual depreciation charge for R&D-exclusive use, NOT the full purchase price. Do not present this BOM as generating 30% on its total value.
B90: Recoverable VAT at 20% (cash-timing) | D90: =D89*0.2 -> 10799.4 | I90: JEI: companies incorporated from 1 January 2024 onward lose the corporate income tax exemption; only the employer social-charge exemption survives.
B91: Physical assets TTC (pre-recovery) | D91: =D89*1.2+D88 -> 65696.4
B92: Operating budget reference | D92: 697500 | I92: ROBOT PLATFORM – deliberately not purchased. Physical validation runs on humanoid units supplied by manufacturers under partnership or evaluation agreements, avoiding significant CapEx and giving access to multiple morphologies instead of a single chassis. Freight, duty and ATA carnet responsibility are set in the partnership agreement, and insurance is extended to third‑party equipment held in custody.
B93: Share of operating budget | D93: =D86/D92 -> 0.11741505 | I93: DEFERRED, NOT BUDGETED: simulation-as-a-service (5.000-25.000EUR, only if simulation is not built in-house), spare capture units (~18.000,00EUR, rejected in favour of the contingency reserve).
B94: Raise reference (750k) | D94: 750000 | I94: SINGLE POINT OF FAILURE: one Xsens suit, one Delsys kit, one MANUS glove pair, one workstation, no redundancy. Mitigation is warranty coverage plus the 2.600,00EUR contingency reserve, not spare units. Disclosed and priced rather than ignored.
B95: Share of raise | D95: =D86/D94 -> 0.109196

Sheet HQ & lab est.
A1: HQ & LAB OPERATING COST PLAN
A2: 18-month headquarters, lab occupancy and core-team hosting estimate. Monthly cash-planning view; assumptions and provisional items are identified in the notes.
A3: CATEGORY | B3: ITEM | C3: Qty | D3: M1 | E3: M2 | F3: M3 | G3: M4 | H3: M5 | I3: M6 | J3: M7 | K3: M8 | L3: M9 | M3: M10 | N3: M11 | O3: M12 | P3: M13 | Q3: M14 | R3: M15 | S3: M16 | T3: M17 | U3: M18 | V3: TOTAL 12M | W3: TOTAL 18M | X3: COST TYPE | Y3: BASIS | Z3: NOTES
A4: OCCUPANCY & LEASE
A5: Occupancy & Lease | B5: Rent | C5: 18 | D5: 5000 | E5: 5000 | F5: 5000 | G5: 5000 | H5: 5000 | I5: 5000 | J5: 5000 | K5: 5000 | L5: 5000 | M5: 5000 | N5: 5000 | O5: 5000 | P5: 5000 | Q5: 5000 | R5: 5000 | S5: 5000 | T5: 5000 | U5: 5000 | V5: =SUM(D5:O5) -> 60000 | W5: =SUM(D5:U5) -> 90000 | X5: OpEx | Y5: €5,000 / month | Z5: User-provided estimate; recurring from M1 to M18.
A6: Occupancy & Lease | B6: Premises / tenant liability insurance | C6: 18 | D6: 50 | E6: 50 | F6: 50 | G6: 50 | H6: 50 | I6: 50 | J6: 50 | K6: 50 | L6: 50 | M6: 50 | N6: 50 | O6: 50 | P6: 50 | Q6: 50 | R6: 50 | S6: 50 | T6: 50 | U6: 50 | V6: =SUM(D6:O6) -> 600 | W6: =SUM(D6:U6) -> 900 | X6: OpEx | Y6: €50 / month | Z6: User-provided estimate; separate from equipment insurance in the BOM.
A7: Occupancy & Lease | B7: Security deposit (recoverable) | C7: 1 | D7: 10000 | V7: =SUM(D7:O7) -> 10000 | W7: =SUM(D7:U7) -> 10000 | X7: Working Capital | Y7: 2 months of rent; paid M1 | Z7: Provisional assumption: €10,000. Cash requirement, not an operating expense.
A8: Occupancy & Lease | B8: Lease, agency, legal and move-in fees | C8: 1 | D8: 5000 | V8: =SUM(D8:O8) -> 5000 | W8: =SUM(D8:U8) -> 5000 | X8: OpEx | Y8: One-off provision; M1 | Z8: Provisional €5,000 pending property and lease terms.
B9: Occupancy & Lease — SUBTOTAL | D9: =SUM(D5:D8) -> 20050 | E9: =SUM(E5:E8) -> 5050 | F9: =SUM(F5:F8) -> 5050 | G9: =SUM(G5:G8) -> 5050 | H9: =SUM(H5:H8) -> 5050 | I9: =SUM(I5:I8) -> 5050 | J9: =SUM(J5:J8) -> 5050 | K9: =SUM(K5:K8) -> 5050 | ... W9: =SUM(W5:W8) -> 105900
A11: FACILITIES & UTILITIES
A12: Facilities & Utilities | B12: Electricity, heating and water | C12: 18 | D12: 100 | E12: 100 | F12: 100 | G12: 100 | H12: 100 | I12: 100 | J12: 100 | K12: 100 | L12: 100 | M12: 100 | N12: 100 | O12: 100 | P12: 100 | Q12: 100 | R12: 100 | S12: 100 | T12: 100 | U12: 100 | V12: =SUM(D12:O12) -> 1200 | W12: =SUM(D12:U12) -> 1800 | X12: OpEx | Y12: €100 / month | Z12: User-provided utility estimate; validate against property size and lab energy load.
A13: Facilities & Utilities | B13: Business internet / telecom | C13: 18 | D13: 100 | E13: 100 | F13: 100 | G13: 100 | H13: 100 | I13: 100 | J13: 100 | K13: 100 | L13: 100 | M13: 100 | N13: 100 | O13: 100 | P13: 100 | Q13: 100 | R13: 100 | S13: 100 | T13: 100 | U13: 100 | V13: =SUM(D13:O13) -> 1200 | W13: =SUM(D13:U13) -> 1800 | X13: OpEx | Y13: €100 / month | Z13: Provisional estimate added separately from utilities.
A14: Facilities & Utilities | B14: Cleaning and household supplies | C14: 18 | D14: 250 | E14: 250 | F14: 250 | G14: 250 | H14: 250 | I14: 250 | J14: 250 | K14: 250 | L14: 250 | M14: 250 | N14: 250 | O14: 250 | P14: 250 | Q14: 250 | R14: 250 | S14: 250 | T14: 250 | U14: 250 | V14: =SUM(D14:O14) -> 3000 | W14: =SUM(D14:U14) -> 4500 | X14: OpEx | Y14: €250 / month | Z14: Provisional estimate for shared living and work areas.
A15: Facilities & Utilities | B15: Minor maintenance and repairs | C15: 18 | D15: 150 | E15: 150 | F15: 150 | G15: 150 | H15: 150 | I15: 150 | J15: 150 | K15: 150 | L15: 150 | M15: 150 | N15: 150 | O15: 150 | P15: 150 | Q15: 150 | R15: 150 | S15: 150 | T15: 150 | U15: 150 | V15: =SUM(D15:O15) -> 1800 | W15: =SUM(D15:U15) -> 2700 | X15: OpEx | Y15: €150 / month | Z15: Provisional recurring maintenance reserve.
A16: Facilities & Utilities | B16: Furniture, fit-out and appliances | C16: 1 | D16: 5000 | V16: =SUM(D16:O16) -> 5000 | W16: =SUM(D16:U16) -> 5000 | X16: CapEx | Y16: €5,000 one-off; M1 | Z16: Validated provision: €5,000 for furniture, fit-out and appliances; paid in M1.
B17: Facilities & Utilities — SUBTOTAL | D17: =SUM(D12:D16) -> 5600 | E17: =SUM(E12:E16) -> 600 | F17: =SUM(F12:F16) -> 600 | G17: =SUM(G12:G16) -> 600 | H17: =SUM(H12:H16) -> 600 | I17: =SUM(I12:I16) -> 600 | J17: =SUM(J12:J16) -> 600 | K17: =SUM(K12:K16) -> 600 | ... W17: =SUM(W12:W16) -> 15800
A19: CORE-TEAM HOSTING
A20: Core-team Hosting | B20: Food and shared meals | D20: =250*((VALUE(SUBSTITUTE('Hiring & Compensation Plan'!$C$5,"M",""))<=VALUE(SUBSTITUTE(D$3,"M","")))+(VALUE(SUBSTITUTE('Hiring & Compensation Plan'!$C$10,"M",""))<=VALUE(SUBSTITUTE(D$3,"M","")))+(VALUE(SUBSTITUTE('Hiring & Compensation Plan'!$C$15,"M",""))<=VALUE(SUBSTITUTE(D$3,"M","")))+(VALUE(SUBSTITUTE('Hiring & Compensation Plan'!$C$20,"M",""))<=VALUE(SUBSTITUTE(D$3,"M","")))) -> 250 | E20: =250*((VALUE(SUBSTITUTE('Hiring & Compensation Plan'!$C$5,"M",""))<=VALUE(SUBSTITUTE(E$3,"M","")))+(VALUE(SUBSTITUTE('Hiring & Compensation Plan'!$C$10,"M",""))<=VALUE(SUBSTITUTE(E$3,"M","")))+(VALUE(SUBSTITUTE('Hiring & Compensation Plan'!$C$15,"M",""))<=VALUE(SUBSTITUTE(E$3,"M","")))+(VALUE(SUBSTITUTE('Hiring & Compensation Plan'!$C$20,"M",""))<=VALUE(SUBSTITUTE(E$3,"M","")))) -> 750 | F20: =250*((VALUE(SUBSTITUTE('Hiring & Compensation Plan'!$C$5,"M",""))<=VALUE(SUBSTITUTE(F$3,"M","")))+(VALUE(SUBSTITUTE('Hiring & Compensation Plan'!$C$10,"M",""))<=VALUE(SUBSTITUTE(F$3,"M","")))+(VALUE(SUBSTITUTE('Hiring & Compensation Plan'!$C$15,"M",""))<=VALUE(SUBSTITUTE(F$3,"M","")))+(VALUE(SUBSTITUTE('Hiring & Compensation Plan'!$C$20,"M",""))<=VALUE(SUBSTITUTE(F$3,"M","")))) -> 750 | G20: =250*((VALUE(SUBSTITUTE('Hiring & Compensation Plan'!$C$5,"M",""))<=VALUE(SUBSTITUTE(G$3,"M","")))+(VALUE(SUBSTITUTE('Hiring & Compensation Plan'!$C$10,"M",""))<=VALUE(SUBSTITUTE(G$3,"M","")))+(VALUE(SUBSTITUTE('Hiring & Compensation Plan'!$C$15,"M",""))<=VALUE(SUBSTITUTE(G$3,"M","")))+(VALUE(SUBSTITUTE('Hiring & Compensation Plan'!$C$20,"M",""))<=VALUE(SUBSTITUTE(G$3,"M","")))) -> 750 | H20: =250*((VALUE(SUBSTITUTE('Hiring & Compensation Plan'!$C$5,"M",""))<=VALUE(SUBSTITUTE(H$3,"M","")))+(VALUE(SUBSTITUTE('Hiring & Compensation Plan'!$C$10,"M",""))<=VALUE(SUBSTITUTE(H$3,"M","")))+(VALUE(SUBSTITUTE('Hiring & Compensation Plan'!$C$15,"M",""))<=VALUE(SUBSTITUTE(H$3,"M","")))+(VALUE(SUBSTITUTE('Hiring & Compensation Plan'!$C$20,"M",""))<=VALUE(SUBSTITUTE(H$3,"M","")))) -> 1000 | I20: =250*((VALUE(SUBSTITUTE('Hiring & Compensation Plan'!$C$5,"M",""))<=VALUE(SUBSTITUTE(I$3,"M","")))+(VALUE(SUBSTITUTE('Hiring & Compensation Plan'!$C$10,"M",""))<=VALUE(SUBSTITUTE(I$3,"M","")))+(VALUE(SUBSTITUTE('Hiring & Compensation Plan'!$C$15,"M",""))<=VALUE(SUBSTITUTE(I$3,"M","")))+(VALUE(SUBSTITUTE('Hiring & Compensation Plan'!$C$20,"M",""))<=VALUE(SUBSTITUTE(I$3,"M","")))) -> 1000 | J20: =250*((VALUE(SUBSTITUTE('Hiring & Compensation Plan'!$C$5,"M",""))<=VALUE(SUBSTITUTE(J$3,"M","")))+(VALUE(SUBSTITUTE('Hiring & Compensation Plan'!$C$10,"M",""))<=VALUE(SUBSTITUTE(J$3,"M","")))+(VALUE(SUBSTITUTE('Hiring & Compensation Plan'!$C$15,"M",""))<=VALUE(SUBSTITUTE(J$3,"M","")))+(VALUE(SUBSTITUTE('Hiring & Compensation Plan'!$C$20,"M",""))<=VALUE(SUBSTITUTE(J$3,"M","")))) -> 1000 | K20: =250*((VALUE(SUBSTITUTE('Hiring & Compensation Plan'!$C$5,"M",""))<=VALUE(SUBSTITUTE(K$3,"M","")))+(VALUE(SUBSTITUTE('Hiring & Compensation Plan'!$C$10,"M",""))<=VALUE(SUBSTITUTE(K$3,"M","")))+(VALUE(SUBSTITUTE('Hiring & Compensation Plan'!$C$15,"M",""))<=VALUE(SUBSTITUTE(K$3,"M","")))+(VALUE(SUBSTITUTE('Hiring & Compensation Plan'!$C$20,"M",""))<=VALUE(SUBSTITUTE(K$3,"M","")))) -> 1000 | ... U20: =250*((VALUE(SUBSTITUTE('Hiring & Compensation Plan'!$C$5,"M",""))<=VALUE(SUBSTITUTE(U$3,"M","")))+(VALUE(SUBSTITUTE('Hiring & Compensation Plan'!$C$10,"M",""))<=VALUE(SUBSTITUTE(U$3,"M","")))+(VALUE(SUBSTITUTE('Hiring & Compensation Plan'!$C$15,"M",""))<=VALUE(SUBSTITUTE(U$3,"M","")))+(VALUE(SUBSTITUTE('Hiring & Compensation Plan'!$C$20,"M",""))<=VALUE(SUBSTITUTE(U$3,"M","")))) -> 1000 | V20: =SUM(D20:O20) -> 10500 | W20: =SUM(D20:U20) -> 16500 | X20: OpEx | Y20: €250 / active core-team FTE / month | Z20: Linked to core-team Start Months in the Hiring & Compensation Plan.
B21: Core-team Hosting — SUBTOTAL | D21: =SUM(D20) -> 250 | E21: =SUM(E20) -> 750 | F21: =SUM(F20) -> 750 | G21: =SUM(G20) -> 750 | H21: =SUM(H20) -> 1000 | I21: =SUM(I20) -> 1000 | J21: =SUM(J20) -> 1000 | K21: =SUM(K20) -> 1000 | ... W21: =SUM(W20) -> 16500
A23: OPERATING CONSUMABLES
A24: Operating Consumables | B24: Office and lab consumables / miscellaneous | C24: 18 | D24: 250 | E24: 250 | F24: 250 | G24: 250 | H24: 250 | I24: 250 | J24: 250 | K24: 250 | L24: 250 | M24: 250 | N24: 250 | O24: 250 | P24: 250 | Q24: 250 | R24: 250 | S24: 250 | T24: 250 | U24: 250 | V24: =SUM(D24:O24) -> 3000 | W24: =SUM(D24:U24) -> 4500 | X24: OpEx | Y24: €250 / month | Z24: User-provided estimate; excludes technical hardware already budgeted in the BOM.
B25: Operating Consumables — SUBTOTAL | D25: =SUM(D24) -> 250 | E25: =SUM(E24) -> 250 | F25: =SUM(F24) -> 250 | G25: =SUM(G24) -> 250 | H25: =SUM(H24) -> 250 | I25: =SUM(I24) -> 250 | J25: =SUM(J24) -> 250 | K25: =SUM(K24) -> 250 | ... W25: =SUM(W24) -> 4500
A27: RISK PROVISION
A28: Risk Provision | B28: Operating contingency reserve | C28: 18 | D28: =5%*SUM(D5:D6,D12:D15,D20,D24) -> 307.5 | E28: =5%*SUM(E5:E6,E12:E15,E20,E24) -> 332.5 | F28: =5%*SUM(F5:F6,F12:F15,F20,F24) -> 332.5 | G28: =5%*SUM(G5:G6,G12:G15,G20,G24) -> 332.5 | H28: =5%*SUM(H5:H6,H12:H15,H20,H24) -> 345 | I28: =5%*SUM(I5:I6,I12:I15,I20,I24) -> 345 | J28: =5%*SUM(J5:J6,J12:J15,J20,J24) -> 345 | K28: =5%*SUM(K5:K6,K12:K15,K20,K24) -> 345 | ... U28: =5%*SUM(U5:U6,U12:U15,U20,U24) -> 345 | V28: =SUM(D28:O28) -> 4065 | W28: =SUM(D28:U28) -> 6135 | X28: Reserve | Y28: 5% of recurring HQ operating costs | Z28: Formula-driven; excludes deposit, entry fees and furniture/fit-out.
B29: Risk Provision — SUBTOTAL | D29: =SUM(D28) -> 307.5 | E29: =SUM(E28) -> 332.5 | F29: =SUM(F28) -> 332.5 | G29: =SUM(G28) -> 332.5 | H29: =SUM(H28) -> 345 | I29: =SUM(I28) -> 345 | J29: =SUM(J28) -> 345 | K29: =SUM(K28) -> 345 | ... W29: =SUM(W28) -> 6135
B31: TOTAL HQ & LAB — 18-MONTH CASH PLAN | D31: =D9+D17+D21+D25+D29 -> 26457.5 | E31: =E9+E17+E21+E25+E29 -> 6982.5 | F31: =F9+F17+F21+F25+F29 -> 6982.5 | G31: =G9+G17+G21+G25+G29 -> 6982.5 | H31: =H9+H17+H21+H25+H29 -> 7245 | I31: =I9+I17+I21+I25+I29 -> 7245 | J31: =J9+J17+J21+J25+J29 -> 7245 | K31: =K9+K17+K21+K25+K29 -> 7245 | ... W31: =W9+W17+W21+W25+W29 -> 148835
A34: EXECUTIVE SUMMARY | H34: NOTES & METHODOLOGY — HQ & LAB
A35: Category | B35: Total 12M | C35: Total 18M | D35: % of 18M total | E35: Cost behavior | F35: Scope
A36: OCCUPANCY & LEASE | B36: =V9 -> 75600 | C36: =W9 -> 105900 | D36: =C36/$W$31 -> 0.71152619 | E36: Recurring + M1 entry cash | F36: Rent, premises insurance, deposit and entry fees | H36: 1. User-provided assumptions retained unchanged: rent €5,000/month; premises insurance €50/month; utilities €100/month; office/lab miscellaneous €250/month; food €1,000/month at four active core-team FTE. 2. Food is modeled at €250 per active core-team FTE and linked to Start Month cells in the Hiring & Compensation Plan: 1 FTE in M1, 3 FTE in M2–M4 and 4 FTE from M5. 3. Security deposit is provisioned at two months of rent (€10,000), paid in M1 and treated as recoverable working capital rather than OpEx. 4. Lease, agency, legal and move-in fees are provisioned at €5,000 in M1 pending the selected property and lease structure. 5. Added provisional recurring estimates: internet €100/month; cleaning and household supplies €250/month; minor maintenance and repairs €150/month. 6. Furniture, fit-out and appliances are provisioned at €5,000 in M1 as upfront CapEx. 7. The €100/month utilities assumption is retained but should be validated against heating, water, property size and sustained lab-compute electricity consumption. 8. A 5% operating contingency is applied to recurring HQ costs only. It excludes the deposit, move-in fees and furniture/fit-out. 9. VAT treatment is not modeled in this tab. Values are cash-planning estimates and must later be normalized consistently across the financial model. 10. Excluded from this tab: Paris–Toulouse travel, payroll, business taxes/CFE, lab hardware already in the BOM, robot freight and broader corporate overhead.
A37: FACILITIES & UTILITIES | B37: =V17 -> 12200 | C37: =W17 -> 15800 | D37: =C37/$W$31 -> 0.10615783 | E37: Recurring + M1 fit-out | F37: Utilities, connectivity, cleaning, maintenance and fit-out
A38: CORE-TEAM HOSTING | B38: =V21 -> 10500 | C38: =W21 -> 16500 | D38: =C38/$W$31 -> 0.11086102 | E38: Scales with active FTE | F38: Food at €250 per active core-team FTE
A39: OPERATING CONSUMABLES | B39: =V25 -> 3000 | C39: =W25 -> 4500 | D39: =C39/$W$31 -> 0.030234824 | E39: Recurring | F39: Office and general lab consumables
A40: RISK PROVISION | B40: =V29 -> 4065 | C40: =W29 -> 6135 | D40: =C40/$W$31 -> 0.041220143 | E40: Formula-driven | F40: 5% contingency on recurring HQ operating costs
A41: GRAND TOTAL | B41: =SUM(B36:B40) -> 105365 | C41: =SUM(C36:C40) -> 148835 | D41: 1
A43: HQ & LAB KPIs
A44: Steady-state monthly HQ & lab cost | B44: =H31 -> 7245
A45: One-off entry cash requirements | B45: =W7+W8+W16 -> 20000
A46: Recoverable security deposit | B46: =W7 -> 10000
A47: 18M operating cost excl. recoverable deposit | B47: =W31-W7 -> 138835
A48: Food provision per active core-team FTE | B48: =250 -> 250

Sheet Other expenses
A1: STRATEGIC OPERATIONS, TRAVEL & PROFESSIONAL SERVICES
A2: 18-month operating budget for targeted expertise, partnership travel, core-team mobility, strategic hospitality and essential corporate services. No events or broad representation budget.
A3: CATEGORY | B3: ITEM | C3: Qty | D3: M1 | E3: M2 | F3: M3 | G3: M4 | H3: M5 | I3: M6 | J3: M7 | K3: M8 | L3: M9 | M3: M10 | N3: M11 | O3: M12 | P3: M13 | Q3: M14 | R3: M15 | S3: M16 | T3: M17 | U3: M18 | V3: TOTAL 12M | W3: TOTAL 18M | X3: COST TYPE | Y3: BASIS | Z3: NOTES
A4: ADVISORY & PROFESSIONAL SERVICES
A5: Advisory & Professional Services | B5: Robotics / embodied AI expert consultations | C5: 6 | E5: 1000 | G5: 1000 | I5: 1000 | K5: 2000 | N5: 2000 | Q5: 3000 | V5: =SUM(D5:O5) -> 7000 | W5: =SUM(D5:U5) -> 10000 | X5: OpEx | Y5: 6 targeted engagements; €10,000 total | Z5: User-defined envelope: 3 × €1,000, 2 × €2,000 and 1 × €3,000.
A6: Advisory & Professional Services | B6: Accounting, payroll and corporate administration | C6: 18 | D6: 500 | E6: 500 | F6: 500 | G6: 500 | H6: 500 | I6: 500 | J6: 500 | K6: 500 | L6: 500 | M6: 500 | N6: 500 | O6: 500 | P6: 500 | Q6: 500 | R6: 500 | S6: 500 | T6: 500 | U6: 500 | V6: =SUM(D6:O6) -> 6000 | W6: =SUM(D6:U6) -> 9000 | X6: OpEx | Y6: €500 / month | Z6: Provisional recurring support for bookkeeping, payroll administration, annual accounts and routine filings.
B7: Advisory & Professional Services — SUBTOTAL | D7: =SUM(D5:D6) -> 500 | E7: =SUM(E5:E6) -> 1500 | F7: =SUM(F5:F6) -> 500 | G7: =SUM(G5:G6) -> 1500 | H7: =SUM(H5:H6) -> 500 | I7: =SUM(I5:I6) -> 1500 | J7: =SUM(J5:J6) -> 500 | K7: =SUM(K5:K6) -> 2500 | ... W7: =SUM(W5:W6) -> 19000
A9: TRAVEL & PARTNERSHIP DEVELOPMENT
A10: Travel & Partnership Development | B10: Core-team Paris–Toulouse mobility | D10: =200*((VALUE(SUBSTITUTE('Hiring & Compensation Plan'!$C$10,"M",""))<=VALUE(SUBSTITUTE(D$3,"M","")))+(VALUE(SUBSTITUTE('Hiring & Compensation Plan'!$C$15,"M",""))<=VALUE(SUBSTITUTE(D$3,"M","")))+(VALUE(SUBSTITUTE('Hiring & Compensation Plan'!$C$20,"M",""))<=VALUE(SUBSTITUTE(D$3,"M","")))) -> 0 | E10: =200*((VALUE(SUBSTITUTE('Hiring & Compensation Plan'!$C$10,"M",""))<=VALUE(SUBSTITUTE(E$3,"M","")))+(VALUE(SUBSTITUTE('Hiring & Compensation Plan'!$C$15,"M",""))<=VALUE(SUBSTITUTE(E$3,"M","")))+(VALUE(SUBSTITUTE('Hiring & Compensation Plan'!$C$20,"M",""))<=VALUE(SUBSTITUTE(E$3,"M","")))) -> 400 | F10: =200*((VALUE(SUBSTITUTE('Hiring & Compensation Plan'!$C$10,"M",""))<=VALUE(SUBSTITUTE(F$3,"M","")))+(VALUE(SUBSTITUTE('Hiring & Compensation Plan'!$C$15,"M",""))<=VALUE(SUBSTITUTE(F$3,"M","")))+(VALUE(SUBSTITUTE('Hiring & Compensation Plan'!$C$20,"M",""))<=VALUE(SUBSTITUTE(F$3,"M","")))) -> 400 | G10: =200*((VALUE(SUBSTITUTE('Hiring & Compensation Plan'!$C$10,"M",""))<=VALUE(SUBSTITUTE(G$3,"M","")))+(VALUE(SUBSTITUTE('Hiring & Compensation Plan'!$C$15,"M",""))<=VALUE(SUBSTITUTE(G$3,"M","")))+(VALUE(SUBSTITUTE('Hiring & Compensation Plan'!$C$20,"M",""))<=VALUE(SUBSTITUTE(G$3,"M","")))) -> 400 | H10: =200*((VALUE(SUBSTITUTE('Hiring & Compensation Plan'!$C$10,"M",""))<=VALUE(SUBSTITUTE(H$3,"M","")))+(VALUE(SUBSTITUTE('Hiring & Compensation Plan'!$C$15,"M",""))<=VALUE(SUBSTITUTE(H$3,"M","")))+(VALUE(SUBSTITUTE('Hiring & Compensation Plan'!$C$20,"M",""))<=VALUE(SUBSTITUTE(H$3,"M","")))) -> 600 | I10: =200*((VALUE(SUBSTITUTE('Hiring & Compensation Plan'!$C$10,"M",""))<=VALUE(SUBSTITUTE(I$3,"M","")))+(VALUE(SUBSTITUTE('Hiring & Compensation Plan'!$C$15,"M",""))<=VALUE(SUBSTITUTE(I$3,"M","")))+(VALUE(SUBSTITUTE('Hiring & Compensation Plan'!$C$20,"M",""))<=VALUE(SUBSTITUTE(I$3,"M","")))) -> 600 | J10: =200*((VALUE(SUBSTITUTE('Hiring & Compensation Plan'!$C$10,"M",""))<=VALUE(SUBSTITUTE(J$3,"M","")))+(VALUE(SUBSTITUTE('Hiring & Compensation Plan'!$C$15,"M",""))<=VALUE(SUBSTITUTE(J$3,"M","")))+(VALUE(SUBSTITUTE('Hiring & Compensation Plan'!$C$20,"M",""))<=VALUE(SUBSTITUTE(J$3,"M","")))) -> 600 | K10: =200*((VALUE(SUBSTITUTE('Hiring & Compensation Plan'!$C$10,"M",""))<=VALUE(SUBSTITUTE(K$3,"M","")))+(VALUE(SUBSTITUTE('Hiring & Compensation Plan'!$C$15,"M",""))<=VALUE(SUBSTITUTE(K$3,"M","")))+(VALUE(SUBSTITUTE('Hiring & Compensation Plan'!$C$20,"M",""))<=VALUE(SUBSTITUTE(K$3,"M","")))) -> 600 | ... U10: =200*((VALUE(SUBSTITUTE('Hiring & Compensation Plan'!$C$10,"M",""))<=VALUE(SUBSTITUTE(U$3,"M","")))+(VALUE(SUBSTITUTE('Hiring & Compensation Plan'!$C$15,"M",""))<=VALUE(SUBSTITUTE(U$3,"M","")))+(VALUE(SUBSTITUTE('Hiring & Compensation Plan'!$C$20,"M",""))<=VALUE(SUBSTITUTE(U$3,"M","")))) -> 600 | V10: =SUM(D10:O10) -> 6000 | W10: =SUM(D10:U10) -> 9600 | X10: OpEx | Y10: €200 / active non-local member / month | Z10: Formula-linked to Joseph, Dali and Nader Start Months; assumes one necessary round trip per active member per month.
A11: Travel & Partnership Development | B11: International partnership missions | C11: 3 | I11: 3000 | N11: 3000 | S11: 3000 | V11: =SUM(D11:O11) -> 6000 | W11: =SUM(D11:U11) -> 9000 | X11: OpEx | Y11: 3 missions × €3,000 | Z11: Rare, targeted missions only; envelope includes transport, hotel, meals, local mobility and eSIM.
A12: Travel & Partnership Development | B12: Partner logistics, shipping and customs | C12: 3 | I12: 1500 | N12: 1500 | S12: 2000 | V12: =SUM(D12:O12) -> 3000 | W12: =SUM(D12:U12) -> 5000 | X12: OpEx | Y12: Event-driven provision | Z12: Provisional transport of samples, sensors or partner equipment; excludes robot purchase.
B13: Travel & Partnership Development — SUBTOTAL | D13: =SUM(D10:D12) -> 0 | E13: =SUM(E10:E12) -> 400 | F13: =SUM(F10:F12) -> 400 | G13: =SUM(G10:G12) -> 400 | H13: =SUM(H10:H12) -> 600 | I13: =SUM(I10:I12) -> 5100 | J13: =SUM(J10:J12) -> 600 | K13: =SUM(K10:K12) -> 600 | ... W13: =SUM(W10:W12) -> 23600
A15: STRATEGIC HOSPITALITY
A16: Strategic Hospitality | B16: Investor and key-profile working meals | C16: 16 | F16: 200 | G16: 200 | H16: 200 | I16: 200 | J16: 200 | K16: 200 | L16: 200 | M16: 200 | N16: 200 | O16: 200 | P16: 200 | Q16: 200 | R16: 200 | S16: 200 | T16: 200 | U16: 200 | V16: =SUM(D16:O16) -> 2000 | W16: =SUM(D16:U16) -> 3200 | X16: OpEx | Y16: €200 / month from M3 | Z16: Small controlled envelope for substantive investor, advisor and partner meetings.
B17: Strategic Hospitality — SUBTOTAL | D17: =SUM(D16) -> 0 | E17: =SUM(E16) -> 0 | F17: =SUM(F16) -> 200 | G17: =SUM(G16) -> 200 | H17: =SUM(H16) -> 200 | I17: =SUM(I16) -> 200 | J17: =SUM(J16) -> 200 | K17: =SUM(K16) -> 200 | ... W17: =SUM(W16) -> 3200
A19: CORPORATE SYSTEMS & ADMIN
A20: Corporate Systems & Admin | B20: General SaaS, collaboration and security tools | C20: 18 | D20: 250 | E20: 250 | F20: 250 | G20: 250 | H20: 250 | I20: 250 | J20: 250 | K20: 250 | L20: 250 | M20: 250 | N20: 250 | O20: 250 | P20: 250 | Q20: 250 | R20: 250 | S20: 250 | T20: 250 | U20: 250 | V20: =SUM(D20:O20) -> 3000 | W20: =SUM(D20:U20) -> 4500 | X20: OpEx | Y20: €250 / month | Z20: Provisional envelope for workspace, code collaboration, documentation, communication and account security; excludes BOM-specific tools.
A21: Corporate Systems & Admin | B21: Banking, payment and administrative fees | C21: 18 | D21: 100 | E21: 100 | F21: 100 | G21: 100 | H21: 100 | I21: 100 | J21: 100 | K21: 100 | L21: 100 | M21: 100 | N21: 100 | O21: 100 | P21: 100 | Q21: 100 | R21: 100 | S21: 100 | T21: 100 | U21: 100 | V21: =SUM(D21:O21) -> 1200 | W21: =SUM(D21:U21) -> 1800 | X21: OpEx | Y21: €100 / month | Z21: Provisional recurring corporate administration envelope.
B22: Corporate Systems & Admin — SUBTOTAL | D22: =SUM(D20:D21) -> 350 | E22: =SUM(E20:E21) -> 350 | F22: =SUM(F20:F21) -> 350 | G22: =SUM(G20:G21) -> 350 | H22: =SUM(H20:H21) -> 350 | I22: =SUM(I20:I21) -> 350 | J22: =SUM(J20:J21) -> 350 | K22: =SUM(K20:K21) -> 350 | ... W22: =SUM(W20:W21) -> 6300
A24: LEGAL, IP & RECRUITMENT
A25: Legal, IP & Recruitment | B25: Legal, partnership and investment documentation | C25: 4 | E25: 2000 | I25: 2000 | M25: 3000 | R25: 3000 | V25: =SUM(D25:O25) -> 7000 | W25: =SUM(D25:U25) -> 10000 | X25: OpEx | Y25: €10,000 staged provision | Z25: Contracts, partnership agreements, employment matters and financing documentation.
A26: Legal, IP & Recruitment | B26: IP strategy, patentability and freedom-to-operate work | C26: 2 | L26: 5000 | R26: 5000 | V26: =SUM(D26:O26) -> 5000 | W26: =SUM(D26:U26) -> 10000 | X26: OpEx | Y26: €10,000 staged provision | Z26: Initial IP landscaping and targeted specialist work; filing strategy remains scope-dependent.
A27: Legal, IP & Recruitment | B27: Recruitment, sourcing and technical assessment | C27: 1 | L27: 3000 | V27: =SUM(D27:O27) -> 3000 | W27: =SUM(D27:U27) -> 3000 | X27: OpEx | Y27: €3,000 event-driven | Z27: Small provision for a future specialist hire; excludes agency-scale recruitment.
A28: Legal, IP & Recruitment | B28: Corporate liability / cyber / D&O insurance | C28: 2 | D28: 2000 | P28: 2000 | V28: =SUM(D28:O28) -> 2000 | W28: =SUM(D28:U28) -> 4000 | X28: OpEx | Y28: €2,000 annual; M1 and M13 | Z28: Validated €4,000 cash provision covering corporate liability/RC Pro, cyber and D&O: €2,000 at M1 and renewal at M13; separate from premises and equipment insurance.
B29: Legal, IP & Recruitment — SUBTOTAL | D29: =SUM(D25:D28) -> 2000 | E29: =SUM(E25:E28) -> 2000 | F29: =SUM(F25:F28) -> 0 | G29: =SUM(G25:G28) -> 0 | H29: =SUM(H25:H28) -> 0 | I29: =SUM(I25:I28) -> 2000 | J29: =SUM(J25:J28) -> 0 | K29: =SUM(K25:K28) -> 0 | ... W29: =SUM(W25:W28) -> 27000
A31: RISK PROVISION
A32: Risk Provision | B32: Variable operations contingency | C32: 18 | D32: =10%*SUM(D5,D10:D12,D16,D25:D27) -> 0 | E32: =10%*SUM(E5,E10:E12,E16,E25:E27) -> 340 | F32: =10%*SUM(F5,F10:F12,F16,F25:F27) -> 60 | G32: =10%*SUM(G5,G10:G12,G16,G25:G27) -> 160 | H32: =10%*SUM(H5,H10:H12,H16,H25:H27) -> 80 | I32: =10%*SUM(I5,I10:I12,I16,I25:I27) -> 830 | J32: =10%*SUM(J5,J10:J12,J16,J25:J27) -> 80 | K32: =10%*SUM(K5,K10:K12,K16,K25:K27) -> 280 | ... U32: =10%*SUM(U5,U10:U12,U16,U25:U27) -> 80 | V32: =SUM(D32:O32) -> 3900 | W32: =SUM(D32:U32) -> 5980 | X32: Reserve | Y32: 10% of variable / event-driven costs | Z32: Applied to consulting, travel, hospitality, legal, IP, recruitment and partner logistics; excludes recurring accounting, SaaS and bank fees.
B33: Risk Provision — SUBTOTAL | D33: =SUM(D32) -> 0 | E33: =SUM(E32) -> 340 | F33: =SUM(F32) -> 60 | G33: =SUM(G32) -> 160 | H33: =SUM(H32) -> 80 | I33: =SUM(I32) -> 830 | J33: =SUM(J32) -> 80 | K33: =SUM(K32) -> 280 | ... W33: =SUM(W32) -> 5980
B35: TOTAL STRATEGIC OPERATIONS & TRAVEL — 18-MONTH PLAN | D35: =D7+D13+D17+D22+D29+D33 -> 2850 | E35: =E7+E13+E17+E22+E29+E33 -> 4590 | F35: =F7+F13+F17+F22+F29+F33 -> 1510 | G35: =G7+G13+G17+G22+G29+G33 -> 2610 | H35: =H7+H13+H17+H22+H29+H33 -> 1730 | I35: =I7+I13+I17+I22+I29+I33 -> 9980 | J35: =J7+J13+J17+J22+J29+J33 -> 1730 | K35: =K7+K13+K17+K22+K29+K33 -> 3930 | ... W35: =W7+W13+W17+W22+W29+W33 -> 85080
A38: EXECUTIVE SUMMARY | H38: NOTES & METHODOLOGY — STRATEGIC OPERATIONS
A39: Category | B39: Total 12M | C39: Total 18M | D39: % of 18M total | E39: Cost behavior | F39: Scope | H39: 1. Recommended tab name: “Strategic Ops & Travel”. “Other expenses” is too generic for an investor-facing model. 2. Expert consulting totals €10,000 exactly: three €1,000 sessions, two €2,000 assignments and one €3,000 deep engagement, staged from M2 to M14. 3. Paris–Toulouse mobility is modeled at €200 per active non-local core-team member per month, linked to Joseph, Dali and Nader Start Months. This assumes one necessary round trip each month. 4. International travel is limited to three targeted partnership missions at €3,000 each. Transport, hotel, meals, local transport and eSIM are included; conferences, events and general representation are excluded. 5. Strategic hospitality is capped at €200/month from M3 and limited to substantive meetings with investors, advisors, technical experts or partners. 6. Added essential provisions: accounting/payroll administration €500/month; general SaaS €250/month; bank/admin fees €100/month; legal documentation €10,000; IP/FTO work €10,000; recruitment €3,000; partner logistics €5,000. 7. Corporate liability, cyber and D&O insurance is provisioned at €4,000 cash over 18 months: €2,000 at M1 and €2,000 renewal at M13. It remains subject to broker quotes and is separate from premises and equipment insurance. 8. A 10% contingency applies only to variable and event-driven operational costs; it excludes recurring accounting, SaaS, banking and insurance lines. 9. VAT treatment is not modeled in this tab. Values are cash-planning estimates and should later be normalized consistently across the full financial model. 10. Excluded: product marketing, paid events, broad business development, sales commissions, robot purchase, payroll, HQ costs and infrastructure already modeled elsewhere.
A40: ADVISORY & PROFESSIONAL SERVICES | B40: =V7 -> 13000 | C40: =W7 -> 19000 | D40: =C40/$W$35 -> 0.22331923 | E40: Recurring + milestone-based | F40: Expert consultations and accounting/admin
A41: TRAVEL & PARTNERSHIP DEVELOPMENT | B41: =V13 -> 15000 | C41: =W13 -> 23600 | D41: =C41/$W$35 -> 0.27738599 | E41: FTE-linked + event-driven | F41: Domestic mobility, rare international missions and logistics
A42: STRATEGIC HOSPITALITY | B42: =V17 -> 2000 | C42: =W17 -> 3200 | D42: =C42/$W$35 -> 0.03761166 | E42: Controlled recurring envelope | F42: Investor and key-profile working meals
A43: CORPORATE SYSTEMS & ADMIN | B43: =V22 -> 4200 | C43: =W22 -> 6300 | D43: =C43/$W$35 -> 0.074047955 | E43: Recurring | F43: General SaaS and corporate administration
A44: LEGAL, IP & RECRUITMENT | B44: =V29 -> 17000 | C44: =W29 -> 27000 | D44: =C44/$W$35 -> 0.31734838 | E44: Milestone-based + annual insurance | F44: Contracts, IP work, targeted recruitment and corporate insurance
A45: RISK PROVISION | B45: =V33 -> 3900 | C45: =W33 -> 5980 | D45: =C45/$W$35 -> 0.070286789 | E45: Formula-driven | F45: 10% contingency on variable and event-driven costs
A46: GRAND TOTAL | B46: =SUM(B40:B45) -> 55100 | C46: =SUM(C40:C45) -> 85080 | D46: 1
A48: OPERATIONS KPIs
A49: Expert consulting envelope | B49: =W5 -> 10000
A50: Core-team domestic mobility | B50: =W10 -> 9600
A51: International missions and partner logistics | B51: =W11+W12 -> 14000
A52: Professional services, legal and IP | B52: =W5+W6+W25+W26 -> 39000
A53: Strategic hospitality | B53: =W17 -> 3200
A54: 18M strategic operations budget | B54: =W35 -> 85080
A55: Average monthly operations budget | B55: =W35/18 -> 4726.6667
A56: Variable-cost contingency | B56: =W33 -> 5980

Sheet Cash Flow & Runway
A1: COGNITRONICS — CASH FLOW & RUNWAY
A2: Editable 18-month scenario cockpit · funding timing, team compensation, infrastructure and dependent operating costs
A3: Yellow cells are editable scenario inputs. Blank overrides preserve the linked baseline. M0 is the financing event before M1 operations; all source tabs remain unchanged.
A5: SCENARIO OUTPUTS
A6: Metric | B6: Value | C6: Interpretation
A7: Full operating months funded | B7: {=IFERROR(MATCH(TRUE,C73:T73<0,0)-1,18)} -> 18 | C7: Completed months before the first negative ending balance.
A8: First cash-shortfall month | B8: {=IFERROR(INDEX(C51:T51,1,MATCH(TRUE,C73:T73<0,0)),"None through M18")} -> None through M18 | C8: A later SAFE cannot bridge a shortfall that occurs before its closing.
A9: Minimum cash balance | B9: =MIN(B73:T73) -> 43944.42 | C9: Lowest month-end liquidity in the selected scenario.
A10: Cash remaining at M18 | B10: =T73 -> 43944.42 | C10: Ending cash after all modeled inflows and outflows.
A11: Total scenario spend — M1 to M18 | B11: =SUM(C69:T69) -> 653555.58 | C11: Payroll, infrastructure, HQ and strategic operations.
A12: Spend variance vs linked baseline | B12: =SUM(C69:T69)-SUM(C62:T62) -> 0 | C12: Positive means the scenario costs more than the current detailed schedules.
A13: Funding received by M18 | B13: =SUM(B55:T55) -> 697500 | C13: Only tiers whose selected closing month falls within M0–M18.
A14: Model controls | B14: =IF(AND(IF($D$18="Not Closed",99,VALUE(SUBSTITUTE($D$18,"M","")))<=IF($D$19="Not Closed",99,VALUE(SUBSTITUTE($D$19,"M",""))),IF($D$19="Not Closed",99,VALUE(SUBSTITUTE($D$19,"M","")))<=IF($D$20="Not Closed",99,VALUE(SUBSTITUTE($D$20,"M",""))),ABS(SUM(C62:T62)-'Assumptions & Funding'!$C$36)<1),"PASS","REVIEW") -> PASS | C14: Checks sequential SAFE timing and reconciliation to the €653,556 linked baseline.
A16: FUNDING CLOSING CONTROLS
A17: Tier | B17: Allocation (USD) | C17: Allocation (EUR) | D17: Scenario closing month | E17: Order | F17: Status | G17: Mechanics
A18: Tier 1 | B18: ='Assumptions & Funding'!C15 -> 200000 | C18: ='Assumptions & Funding'!D15 -> 186000 | D18: M0 | E18: ='Assumptions & Funding'!B15 -> 1 | F18: Proposed / unclosed | G18: Cash becomes available in the selected month.
A19: Tier 2 | B19: ='Assumptions & Funding'!C16 -> 250000 | C19: ='Assumptions & Funding'!D16 -> 232500 | D19: M3 | E19: ='Assumptions & Funding'!B16 -> 2 | F19: Proposed / unclosed | G19: Cash becomes available in the selected month.
A20: Tier 3 | B20: ='Assumptions & Funding'!C17 -> 300000 | C20: ='Assumptions & Funding'!D17 -> 279000 | D20: M6 | E20: ='Assumptions & Funding'!B17 -> 3 | F20: Proposed / unclosed | G20: Cash becomes available in the selected month.
A21: TOTAL | B21: =SUM(B18:B20) -> 750000 | C21: =SUM(C18:C20) -> 697500 | G21: Initial M0 / M3 / M6 sequence is illustrative and fully editable.
A23: TEAM COMPENSATION SCENARIO
A24: Member | B24: Role | C24: Baseline start | D24: Start override | E24: Effective start | F24: Baseline net / direct fee | G24: Net / fee override | H24: Effective net / fee | I24: Gross ÷ net | J24: JEI charge ÷ gross | K24: Scenario gross | L24: Scenario JEI charges | M24: Scenario monthly TCO | N24: Baseline 18M cost | O24: Scenario 18M cost | P24: Variance
A25: THMS | B25: Founder | C25: ='Hiring & Compensation Plan'!C5 -> M1 | D25: M1 | E25: =IF(D25="",VALUE(SUBSTITUTE(C25,"M","")),VALUE(SUBSTITUTE(D25,"M",""))) -> 1 | F25: ='Hiring & Compensation Plan'!V5 -> 3000 | H25: =IF(G25="",F25,G25) -> 3000 | I25: ='Hiring & Compensation Plan'!V6/'Hiring & Compensation Plan'!V5 -> 1.2987 | J25: ='Hiring & Compensation Plan'!V8/'Hiring & Compensation Plan'!V6 -> 0.29399913 | K25: =H25*I25 -> 3896.1 | L25: =K25*J25 -> 1145.45 | M25: =K25+L25 -> 5041.55 | N25: ='Hiring & Compensation Plan'!X9 -> 89067.56 | O25: =SUM(C77:T77) -> 89067.56 | P25: =O25-N25 -> 0
A26: JSPH | B26: AI / Robotics | C26: ='Hiring & Compensation Plan'!C10 -> M2 | D26: M2 | E26: =IF(D26="",VALUE(SUBSTITUTE(C26,"M","")),VALUE(SUBSTITUTE(D26,"M",""))) -> 2 | F26: ='Hiring & Compensation Plan'!V10 -> 4000 | H26: =IF(G26="",F26,G26) -> 4000 | I26: ='Hiring & Compensation Plan'!V11/'Hiring & Compensation Plan'!V10 -> 1.2987025 | J26: ='Hiring & Compensation Plan'!V13/'Hiring & Compensation Plan'!V11 -> 0.2939992 | K26: =H26*I26 -> 5194.81 | L26: =K26*J26 -> 1527.27 | M26: =K26+L26 -> 6722.08 | N26: ='Hiring & Compensation Plan'!X14 -> 104192.24 | O26: =SUM(C78:T78) -> 104192.24 | P26: =O26-N26 -> 0
A27: DALI | B27: Maths Applied | C27: ='Hiring & Compensation Plan'!C15 -> M2 | D27: M2 | E27: =IF(D27="",VALUE(SUBSTITUTE(C27,"M","")),VALUE(SUBSTITUTE(D27,"M",""))) -> 2 | F27: ='Hiring & Compensation Plan'!V15 -> 2500 | H27: =IF(G27="",F27,G27) -> 2500 | I27: ='Hiring & Compensation Plan'!V16/'Hiring & Compensation Plan'!V15 -> 1.2987 | J27: ='Hiring & Compensation Plan'!V18/'Hiring & Compensation Plan'!V16 -> 0.29400169 | K27: =H27*I27 -> 3246.75 | L27: =K27*J27 -> 954.55 | M27: =K27+L27 -> 4201.3 | N27: ='Hiring & Compensation Plan'!X19 -> 63762.98 | O27: =SUM(C79:T79) -> 63762.98 | P27: =O27-N27 -> 0
A28: NADR | B28: Embedded Systems | C28: ='Hiring & Compensation Plan'!C20 -> M5 | D28: M5 | E28: =IF(D28="",VALUE(SUBSTITUTE(C28,"M","")),VALUE(SUBSTITUTE(D28,"M",""))) -> 5 | F28: ='Hiring & Compensation Plan'!V20 -> 3000 | H28: =IF(G28="",F28,G28) -> 3000 | I28: ='Hiring & Compensation Plan'!V21/'Hiring & Compensation Plan'!V20 -> 1.2987 | J28: ='Hiring & Compensation Plan'!V23/'Hiring & Compensation Plan'!V21 -> 0.29399913 | K28: =H28*I28 -> 3896.1 | L28: =K28*J28 -> 1145.45 | M28: =K28+L28 -> 5041.55 | N28: ='Hiring & Compensation Plan'!X24 -> 67220.8 | O28: =SUM(C80:T80) -> 67220.8 | P28: =O28-N28 -> 0
A29: MAXM | B29: Fractional CTO / direct fee | C29: ='Hiring & Compensation Plan'!C25 -> M2 | D29: M1 | E29: =IF(D29="",VALUE(SUBSTITUTE(C29,"M","")),VALUE(SUBSTITUTE(D29,"M",""))) -> 1 | F29: =MAX('Hiring & Compensation Plan'!E25:V25) -> 2250 | H29: =IF(G29="",F29,G29) -> 2250 | I29: =1 -> 1 | J29: =0 -> 0 | K29: =H29*I29 -> 2250 | L29: =K29*J29 -> 0 | M29: =K29+L29 -> 2250 | N29: ='Hiring & Compensation Plan'!X25 -> 13500 | O29: =SUM(C81:T81) -> 13500 | P29: =O29-N29 -> 0
A30: TOTAL TEAM | N30: =SUM(N25:N29) -> 337743.58 | O30: =SUM(O25:O29) -> 337743.58 | P30: =O30-N30 -> 0
A31: Salary overrides scale and shift each person’s existing monthly TCO profile. Gross and JEI charges use the current stable-stage ratios from the Hiring Plan; MAXM remains a direct-fee profile.
A33: INFRASTRUCTURE SCENARIO
A34: Category | B34: Source subtotal | C34: Baseline 18M | D34: Cost override | E34: Effective budget | F34: Timing shift (months) | G34: Scenario spend through M18 | H34: Variance vs baseline | I34: Remaining after M18
A35: Capture Hardware | B35: BOM row 18 | C35: ='MVP & lab hardware BOM'!W18 -> 27379 | E35: =IF(D35="",C35,D35) -> 27379 | F35: 0 | G35: =SUM(C84:T84) -> 27379 | H35: =G35-C35 -> 0 | I35: =MAX(0,E35-G35) -> 0
A36: Shared Dataset Storage | B36: BOM row 24 | C36: ='MVP & lab hardware BOM'!W24 -> 1300 | E36: =IF(D36="",C36,D36) -> 1300 | F36: 0 | G36: =SUM(C85:T85) -> 1300 | H36: =G36-C36 -> 0 | I36: =MAX(0,E36-G36) -> 0
A37: Development Compute | B37: BOM row 40 | C37: ='MVP & lab hardware BOM'!W40 -> 9880 | E37: =IF(D37="",C37,D37) -> 9880 | F37: 0 | G37: =SUM(C86:T86) -> 9880 | H37: =G37-C37 -> 0 | I37: =MAX(0,E37-G37) -> 0
A38: Embedded AI Compute | B38: BOM row 53 | C38: ='MVP & lab hardware BOM'!W53 -> 11538 | E38: =IF(D38="",C38,D38) -> 11538 | F38: 0 | G38: =SUM(C87:T87) -> 11538 | H38: =G38-C38 -> 0 | I38: =MAX(0,E38-G38) -> 0
A39: Lab Operations & Risk | B39: BOM row 60 | C39: ='MVP & lab hardware BOM'!W60 -> 4800 | E39: =IF(D39="",C39,D39) -> 4800 | F39: 0 | G39: =SUM(C88:T88) -> 4800 | H39: =G39-C39 -> 0 | I39: =MAX(0,E39-G39) -> 0
A40: Cloud Compute (OpEx) | B40: BOM row 68 | C40: ='MVP & lab hardware BOM'!W68 -> 27000 | E40: =IF(D40="",C40,D40) -> 27000 | F40: 0 | G40: =SUM(C89:T89) -> 27000 | H40: =G40-C40 -> 0 | I40: =MAX(0,E40-G40) -> 0
A41: TOTAL INFRASTRUCTURE | C41: =SUM(C35:C40) -> 81897 | E41: =SUM(E35:E40) -> 81897 | G41: =SUM(G35:G40) -> 81897 | H41: =SUM(H35:H40) -> 0 | I41: =SUM(I35:I40) -> 0
A42: Cost overrides scale the linked category profile. Timing shift moves that profile by whole months; positive values delay spending and amounts shifted beyond M18 appear as remaining allocation.
A44: DEPENDENT COST & VAT CONTROLS
A45: Driver | B45: Timing / Basis | C45: Baseline | D45: Override | E45: Effective | F45: Scenario effect
A46: Estimated deductible VAT cash refund | B46: M13 | C46: 0 | D46: 0 | E46: =IF(D46="",C46,D46) -> 0 | F46: Cash inflow only; base case remains €0 until invoice-level deductible VAT is quantified.
A47: HQ food & hosting / active core member / month | B47: M1–M18 | C47: ='HQ & lab est.'!D20 -> 250 | E47: =IF(D47="",C47,D47) -> 250 | F47: Automatically follows effective start months for THMS, JSPH, DALI and NADR.
A48: Paris–Toulouse mobility / active non-local member / month | B48: M1–M18 | C48: ='Other expenses'!E10/2 -> 200 | E48: =IF(D48="",C48,D48) -> 200 | F48: Automatically follows effective start months for JSPH, DALI and NADR.
A50: MONTHLY CASH FLOW
A51: Cash-flow line | B51: M0 | C51: M1 | D51: M2 | E51: M3 | F51: M4 | G51: M5 | H51: M6 | I51: M7 | J51: M8 | K51: M9 | L51: M10 | M51: M11 | N51: M12 | O51: M13 | P51: M14 | Q51: M15 | R51: M16 | S51: M17 | T51: M18 | U51: 18M / END
A52: Tier 1 SAFE inflow | B52: =IF(B$51=$D$18,$C$18,0) -> 186000 | C52: =IF(C$51=$D$18,$C$18,0) -> 0 | D52: =IF(D$51=$D$18,$C$18,0) -> 0 | E52: =IF(E$51=$D$18,$C$18,0) -> 0 | F52: =IF(F$51=$D$18,$C$18,0) -> 0 | G52: =IF(G$51=$D$18,$C$18,0) -> 0 | H52: =IF(H$51=$D$18,$C$18,0) -> 0 | I52: =IF(I$51=$D$18,$C$18,0) -> 0 | ... T52: =IF(T$51=$D$18,$C$18,0) -> 0 | U52: =SUM(B52:T52) -> 186000
A53: Tier 2 SAFE inflow | B53: =IF(B$51=$D$19,$C$19,0) -> 0 | C53: =IF(C$51=$D$19,$C$19,0) -> 0 | D53: =IF(D$51=$D$19,$C$19,0) -> 0 | E53: =IF(E$51=$D$19,$C$19,0) -> 232500 | F53: =IF(F$51=$D$19,$C$19,0) -> 0 | G53: =IF(G$51=$D$19,$C$19,0) -> 0 | H53: =IF(H$51=$D$19,$C$19,0) -> 0 | I53: =IF(I$51=$D$19,$C$19,0) -> 0 | ... T53: =IF(T$51=$D$19,$C$19,0) -> 0 | U53: =SUM(B53:T53) -> 232500
A54: Tier 3 SAFE inflow | B54: =IF(B$51=$D$20,$C$20,0) -> 0 | C54: =IF(C$51=$D$20,$C$20,0) -> 0 | D54: =IF(D$51=$D$20,$C$20,0) -> 0 | E54: =IF(E$51=$D$20,$C$20,0) -> 0 | F54: =IF(F$51=$D$20,$C$20,0) -> 0 | G54: =IF(G$51=$D$20,$C$20,0) -> 0 | H54: =IF(H$51=$D$20,$C$20,0) -> 279000 | I54: =IF(I$51=$D$20,$C$20,0) -> 0 | ... T54: =IF(T$51=$D$20,$C$20,0) -> 0 | U54: =SUM(B54:T54) -> 279000
A55: TOTAL FUNDING INFLOWS | B55: =SUM(B52:B54) -> 186000 | C55: =SUM(C52:C54) -> 0 | D55: =SUM(D52:D54) -> 0 | E55: =SUM(E52:E54) -> 232500 | F55: =SUM(F52:F54) -> 0 | G55: =SUM(G52:G54) -> 0 | H55: =SUM(H52:H54) -> 279000 | I55: =SUM(I52:I54) -> 0 | ... T55: =SUM(T52:T54) -> 0 | U55: =SUM(B55:T55) -> 697500
A57: BASELINE OUTFLOWS
A58: Payroll — linked baseline | B58: 0 | C58: ='Hiring & Compensation Plan'!E27 -> 3361.04 | D58: ='Hiring & Compensation Plan'!F27 -> 11864.6 | E58: ='Hiring & Compensation Plan'!G27 -> 9614.6 | F58: ='Hiring & Compensation Plan'!H27 -> 15694.16 | G58: ='Hiring & Compensation Plan'!I27 -> 16805.2 | H58: ='Hiring & Compensation Plan'!J27 -> 22416.24 | I58: ='Hiring & Compensation Plan'!K27 -> 20166.24 | J58: ='Hiring & Compensation Plan'!L27 -> 21006.5 | ... T58: ='Hiring & Compensation Plan'!V27 -> 21006.5 | U58: =SUM(B58:T58) -> 337743.58
A59: Infrastructure — linked baseline | B59: 0 | C59: ='MVP & lab hardware BOM'!D70 -> 37566.58 | D59: ='MVP & lab hardware BOM'!E70 -> 404.04 | E59: ='MVP & lab hardware BOM'!F70 -> 448.54 | F59: ='MVP & lab hardware BOM'!G70 -> 8262.17 | G59: ='MVP & lab hardware BOM'!H70 -> 828.45 | H59: ='MVP & lab hardware BOM'!I70 -> 981.57 | I59: ='MVP & lab hardware BOM'!J70 -> 1061.04 | J59: ='MVP & lab hardware BOM'!K70 -> 3820.43 | ... T59: ='MVP & lab hardware BOM'!U70 -> 1527.56 | U59: =SUM(B59:T59) -> 81897
A60: HQ & lab — linked baseline | B60: 0 | C60: ='HQ & lab est.'!D31 -> 26457.5 | D60: ='HQ & lab est.'!E31 -> 6982.5 | E60: ='HQ & lab est.'!F31 -> 6982.5 | F60: ='HQ & lab est.'!G31 -> 6982.5 | G60: ='HQ & lab est.'!H31 -> 7245 | H60: ='HQ & lab est.'!I31 -> 7245 | I60: ='HQ & lab est.'!J31 -> 7245 | J60: ='HQ & lab est.'!K31 -> 7245 | ... T60: ='HQ & lab est.'!U31 -> 7245 | U60: =SUM(B60:T60) -> 148835
A61: Strategic operations — linked baseline | B61: 0 | C61: ='Other expenses'!D35 -> 2850 | D61: ='Other expenses'!E35 -> 4590 | E61: ='Other expenses'!F35 -> 1510 | F61: ='Other expenses'!G35 -> 2610 | G61: ='Other expenses'!H35 -> 1730 | H61: ='Other expenses'!I35 -> 9980 | I61: ='Other expenses'!J35 -> 1730 | J61: ='Other expenses'!K35 -> 3930 | ... T61: ='Other expenses'!U35 -> 1730 | U61: =SUM(B61:T61) -> 85080
A62: TOTAL BASELINE OUTFLOWS | B62: 0 | C62: =SUM(C58:C61) -> 70235.12 | D62: =SUM(D58:D61) -> 23841.14 | E62: =SUM(E58:E61) -> 18555.64 | F62: =SUM(F58:F61) -> 33548.83 | G62: =SUM(G58:G61) -> 26608.65 | H62: =SUM(H58:H61) -> 40622.81 | I62: =SUM(I58:I61) -> 30202.28 | J62: =SUM(J58:J61) -> 36001.93 | ... T62: =SUM(T58:T61) -> 31509.06 | U62: =SUM(B62:T62) -> 653555.58
A64: SCENARIO OUTFLOWS
A65: Payroll — scenario | B65: 0 | C65: =C82 -> 5611.04 | D65: =D82 -> 9614.6 | E65: =E82 -> 11864.6 | F65: =F82 -> 13444.16 | G65: =G82 -> 19055.2 | H65: =H82 -> 20166.24 | I65: =I82 -> 20166.24 | J65: =J82 -> 23256.5 | ... T65: =T82 -> 21006.5 | U65: =SUM(B65:T65) -> 337743.58
A66: Infrastructure — scenario | B66: 0 | C66: =C90 -> 37566.58 | D66: =D90 -> 404.04 | E66: =E90 -> 448.54 | F66: =F90 -> 8262.17 | G66: =G90 -> 828.45 | H66: =H90 -> 981.57 | I66: =I90 -> 1061.04 | J66: =J90 -> 3820.43 | ... T66: =T90 -> 1527.56 | U66: =SUM(B66:T66) -> 81897
A67: HQ & lab — scenario | B67: 0 | C67: ='HQ & lab est.'!D31-'HQ & lab est.'!D20+$E$47*COUNTIF($E$25:$E$28,"<="&VALUE(SUBSTITUTE(C$51,"M",""))) -> 26457.5 | D67: ='HQ & lab est.'!E31-'HQ & lab est.'!E20+$E$47*COUNTIF($E$25:$E$28,"<="&VALUE(SUBSTITUTE(D$51,"M",""))) -> 6982.5 | E67: ='HQ & lab est.'!F31-'HQ & lab est.'!F20+$E$47*COUNTIF($E$25:$E$28,"<="&VALUE(SUBSTITUTE(E$51,"M",""))) -> 6982.5 | F67: ='HQ & lab est.'!G31-'HQ & lab est.'!G20+$E$47*COUNTIF($E$25:$E$28,"<="&VALUE(SUBSTITUTE(F$51,"M",""))) -> 6982.5 | G67: ='HQ & lab est.'!H31-'HQ & lab est.'!H20+$E$47*COUNTIF($E$25:$E$28,"<="&VALUE(SUBSTITUTE(G$51,"M",""))) -> 7245 | H67: ='HQ & lab est.'!I31-'HQ & lab est.'!I20+$E$47*COUNTIF($E$25:$E$28,"<="&VALUE(SUBSTITUTE(H$51,"M",""))) -> 7245 | I67: ='HQ & lab est.'!J31-'HQ & lab est.'!J20+$E$47*COUNTIF($E$25:$E$28,"<="&VALUE(SUBSTITUTE(I$51,"M",""))) -> 7245 | J67: ='HQ & lab est.'!K31-'HQ & lab est.'!K20+$E$47*COUNTIF($E$25:$E$28,"<="&VALUE(SUBSTITUTE(J$51,"M",""))) -> 7245 | ... T67: ='HQ & lab est.'!U31-'HQ & lab est.'!U20+$E$47*COUNTIF($E$25:$E$28,"<="&VALUE(SUBSTITUTE(T$51,"M",""))) -> 7245 | U67: =SUM(B67:T67) -> 148835
A68: Strategic operations — scenario | B68: 0 | C68: ='Other expenses'!D35-'Other expenses'!D10+$E$48*COUNTIF($E$26:$E$28,"<="&VALUE(SUBSTITUTE(C$51,"M",""))) -> 2850 | D68: ='Other expenses'!E35-'Other expenses'!E10+$E$48*COUNTIF($E$26:$E$28,"<="&VALUE(SUBSTITUTE(D$51,"M",""))) -> 4590 | E68: ='Other expenses'!F35-'Other expenses'!F10+$E$48*COUNTIF($E$26:$E$28,"<="&VALUE(SUBSTITUTE(E$51,"M",""))) -> 1510 | F68: ='Other expenses'!G35-'Other expenses'!G10+$E$48*COUNTIF($E$26:$E$28,"<="&VALUE(SUBSTITUTE(F$51,"M",""))) -> 2610 | G68: ='Other expenses'!H35-'Other expenses'!H10+$E$48*COUNTIF($E$26:$E$28,"<="&VALUE(SUBSTITUTE(G$51,"M",""))) -> 1730 | H68: ='Other expenses'!I35-'Other expenses'!I10+$E$48*COUNTIF($E$26:$E$28,"<="&VALUE(SUBSTITUTE(H$51,"M",""))) -> 9980 | I68: ='Other expenses'!J35-'Other expenses'!J10+$E$48*COUNTIF($E$26:$E$28,"<="&VALUE(SUBSTITUTE(I$51,"M",""))) -> 1730 | J68: ='Other expenses'!K35-'Other expenses'!K10+$E$48*COUNTIF($E$26:$E$28,"<="&VALUE(SUBSTITUTE(J$51,"M",""))) -> 3930 | ... T68: ='Other expenses'!U35-'Other expenses'!U10+$E$48*COUNTIF($E$26:$E$28,"<="&VALUE(SUBSTITUTE(T$51,"M",""))) -> 1730 | U68: =SUM(B68:T68) -> 85080
A69: TOTAL SCENARIO OUTFLOWS | B69: 0 | C69: =SUM(C65:C68) -> 72485.12 | D69: =SUM(D65:D68) -> 21591.14 | E69: =SUM(E65:E68) -> 20805.64 | F69: =SUM(F65:F68) -> 31298.83 | G69: =SUM(G65:G68) -> 28858.65 | H69: =SUM(H65:H68) -> 38372.81 | I69: =SUM(I65:I68) -> 30202.28 | J69: =SUM(J65:J68) -> 38251.93 | ... T69: =SUM(T65:T68) -> 31509.06 | U69: =SUM(B69:T69) -> 653555.58
A70: VAT REFUND INFLOW | B70: 0 | C70: =IF(C$51=$B$46,$E$46,0) -> 0 | D70: =IF(D$51=$B$46,$E$46,0) -> 0 | E70: =IF(E$51=$B$46,$E$46,0) -> 0 | F70: =IF(F$51=$B$46,$E$46,0) -> 0 | G70: =IF(G$51=$B$46,$E$46,0) -> 0 | H70: =IF(H$51=$B$46,$E$46,0) -> 0 | I70: =IF(I$51=$B$46,$E$46,0) -> 0 | J70: =IF(J$51=$B$46,$E$46,0) -> 0 | ... T70: =IF(T$51=$B$46,$E$46,0) -> 0 | U70: =SUM(B70:T70) -> 0
A71: NET CASH FLOW | B71: =B55+B70-B69 -> 186000 | C71: =C55+C70-C69 -> -72485.12 | D71: =D55+D70-D69 -> -21591.14 | E71: =E55+E70-E69 -> 211694.36 | F71: =F55+F70-F69 -> -31298.83 | G71: =G55+G70-G69 -> -28858.65 | H71: =H55+H70-H69 -> 240627.19 | I71: =I55+I70-I69 -> -30202.28 | ... T71: =T55+T70-T69 -> -31509.06 | U71: =SUM(B71:T71) -> 43944.42
A72: OPENING CASH | B72: ='Assumptions & Funding'!B10 -> 0 | C72: =B73 -> 186000 | D72: =C73 -> 113514.88 | E72: =D73 -> 91923.74 | F72: =E73 -> 303618.1 | G72: =F73 -> 272319.27 | H72: =G73 -> 243460.62 | I72: =H73 -> 484087.81 | J72: =I73 -> 453885.53 | ... T72: =S73 -> 75453.48
A73: ENDING CASH | B73: =B72+B71 -> 186000 | C73: =C72+C71 -> 113514.88 | D73: =D72+D71 -> 91923.74 | E73: =E72+E71 -> 303618.1 | F73: =F72+F71 -> 272319.27 | G73: =G72+G71 -> 243460.62 | H73: =H72+H71 -> 484087.81 | I73: =I72+I71 -> 453885.53 | ... T73: =T72+T71 -> 43944.42 | U73: =T73 -> 43944.42
A74: LIQUIDITY STATUS | B74: =IF(B73<0,"CASH SHORTFALL","FUNDED") -> FUNDED | C74: =IF(C73<0,"CASH SHORTFALL","FUNDED") -> FUNDED | D74: =IF(D73<0,"CASH SHORTFALL","FUNDED") -> FUNDED | E74: =IF(E73<0,"CASH SHORTFALL","FUNDED") -> FUNDED | F74: =IF(F73<0,"CASH SHORTFALL","FUNDED") -> FUNDED | G74: =IF(G73<0,"CASH SHORTFALL","FUNDED") -> FUNDED | H74: =IF(H73<0,"CASH SHORTFALL","FUNDED") -> FUNDED | I74: =IF(I73<0,"CASH SHORTFALL","FUNDED") -> FUNDED | ... T74: =IF(T73<0,"CASH SHORTFALL","FUNDED") -> FUNDED | U74: =IF(COUNTIF(B74:T74,"CASH SHORTFALL")>0,"REVIEW","PASS") -> PASS
A76: CALCULATION SUPPORT — TEAM MONTHLY PROFILES
A77: THMS | B77: 0 | C77: {=IF(VALUE(SUBSTITUTE(C$51,"M",""))<$E25,0,IFERROR(INDEX('Hiring & Compensation Plan'!$E$9:$V$9,1,VALUE(SUBSTITUTE(C$51,"M",""))-$E25+VALUE(SUBSTITUTE($C25,"M",""))),0)*IF($F25=0,0,$H25/$F25))} -> 3361.04 | D77: {=IF(VALUE(SUBSTITUTE(D$51,"M",""))<$E25,0,IFERROR(INDEX('Hiring & Compensation Plan'!$E$9:$V$9,1,VALUE(SUBSTITUTE(D$51,"M",""))-$E25+VALUE(SUBSTITUTE($C25,"M",""))),0)*IF($F25=0,0,$H25/$F25))} -> 5041.56 | E77: {=IF(VALUE(SUBSTITUTE(E$51,"M",""))<$E25,0,IFERROR(INDEX('Hiring & Compensation Plan'!$E$9:$V$9,1,VALUE(SUBSTITUTE(E$51,"M",""))-$E25+VALUE(SUBSTITUTE($C25,"M",""))),0)*IF($F25=0,0,$H25/$F25))} -> 5041.56 | F77: {=IF(VALUE(SUBSTITUTE(F$51,"M",""))<$E25,0,IFERROR(INDEX('Hiring & Compensation Plan'!$E$9:$V$9,1,VALUE(SUBSTITUTE(F$51,"M",""))-$E25+VALUE(SUBSTITUTE($C25,"M",""))),0)*IF($F25=0,0,$H25/$F25))} -> 5041.56 | G77: {=IF(VALUE(SUBSTITUTE(G$51,"M",""))<$E25,0,IFERROR(INDEX('Hiring & Compensation Plan'!$E$9:$V$9,1,VALUE(SUBSTITUTE(G$51,"M",""))-$E25+VALUE(SUBSTITUTE($C25,"M",""))),0)*IF($F25=0,0,$H25/$F25))} -> 5041.56 | H77: {=IF(VALUE(SUBSTITUTE(H$51,"M",""))<$E25,0,IFERROR(INDEX('Hiring & Compensation Plan'!$E$9:$V$9,1,VALUE(SUBSTITUTE(H$51,"M",""))-$E25+VALUE(SUBSTITUTE($C25,"M",""))),0)*IF($F25=0,0,$H25/$F25))} -> 5041.56 | I77: {=IF(VALUE(SUBSTITUTE(I$51,"M",""))<$E25,0,IFERROR(INDEX('Hiring & Compensation Plan'!$E$9:$V$9,1,VALUE(SUBSTITUTE(I$51,"M",""))-$E25+VALUE(SUBSTITUTE($C25,"M",""))),0)*IF($F25=0,0,$H25/$F25))} -> 5041.56 | J77: {=IF(VALUE(SUBSTITUTE(J$51,"M",""))<$E25,0,IFERROR(INDEX('Hiring & Compensation Plan'!$E$9:$V$9,1,VALUE(SUBSTITUTE(J$51,"M",""))-$E25+VALUE(SUBSTITUTE($C25,"M",""))),0)*IF($F25=0,0,$H25/$F25))} -> 5041.56 | ... T77: {=IF(VALUE(SUBSTITUTE(T$51,"M",""))<$E25,0,IFERROR(INDEX('Hiring & Compensation Plan'!$E$9:$V$9,1,VALUE(SUBSTITUTE(T$51,"M",""))-$E25+VALUE(SUBSTITUTE($C25,"M",""))),0)*IF($F25=0,0,$H25/$F25))} -> 5041.56 | U77: =SUM(C77:T77) -> 89067.56
A78: JSPH | B78: 0 | C78: {=IF(VALUE(SUBSTITUTE(C$51,"M",""))<$E26,0,IFERROR(INDEX('Hiring & Compensation Plan'!$E$14:$V$14,1,VALUE(SUBSTITUTE(C$51,"M",""))-$E26+VALUE(SUBSTITUTE($C26,"M",""))),0)*IF($F26=0,0,$H26/$F26))} -> 0 | D78: {=IF(VALUE(SUBSTITUTE(D$51,"M",""))<$E26,0,IFERROR(INDEX('Hiring & Compensation Plan'!$E$14:$V$14,1,VALUE(SUBSTITUTE(D$51,"M",""))-$E26+VALUE(SUBSTITUTE($C26,"M",""))),0)*IF($F26=0,0,$H26/$F26))} -> 3361.04 | E78: {=IF(VALUE(SUBSTITUTE(E$51,"M",""))<$E26,0,IFERROR(INDEX('Hiring & Compensation Plan'!$E$14:$V$14,1,VALUE(SUBSTITUTE(E$51,"M",""))-$E26+VALUE(SUBSTITUTE($C26,"M",""))),0)*IF($F26=0,0,$H26/$F26))} -> 3361.04 | F78: {=IF(VALUE(SUBSTITUTE(F$51,"M",""))<$E26,0,IFERROR(INDEX('Hiring & Compensation Plan'!$E$14:$V$14,1,VALUE(SUBSTITUTE(F$51,"M",""))-$E26+VALUE(SUBSTITUTE($C26,"M",""))),0)*IF($F26=0,0,$H26/$F26))} -> 5041.56 | G78: {=IF(VALUE(SUBSTITUTE(G$51,"M",""))<$E26,0,IFERROR(INDEX('Hiring & Compensation Plan'!$E$14:$V$14,1,VALUE(SUBSTITUTE(G$51,"M",""))-$E26+VALUE(SUBSTITUTE($C26,"M",""))),0)*IF($F26=0,0,$H26/$F26))} -> 5041.56 | H78: {=IF(VALUE(SUBSTITUTE(H$51,"M",""))<$E26,0,IFERROR(INDEX('Hiring & Compensation Plan'!$E$14:$V$14,1,VALUE(SUBSTITUTE(H$51,"M",""))-$E26+VALUE(SUBSTITUTE($C26,"M",""))),0)*IF($F26=0,0,$H26/$F26))} -> 6722.08 | I78: {=IF(VALUE(SUBSTITUTE(I$51,"M",""))<$E26,0,IFERROR(INDEX('Hiring & Compensation Plan'!$E$14:$V$14,1,VALUE(SUBSTITUTE(I$51,"M",""))-$E26+VALUE(SUBSTITUTE($C26,"M",""))),0)*IF($F26=0,0,$H26/$F26))} -> 6722.08 | J78: {=IF(VALUE(SUBSTITUTE(J$51,"M",""))<$E26,0,IFERROR(INDEX('Hiring & Compensation Plan'!$E$14:$V$14,1,VALUE(SUBSTITUTE(J$51,"M",""))-$E26+VALUE(SUBSTITUTE($C26,"M",""))),0)*IF($F26=0,0,$H26/$F26))} -> 6722.08 | ... T78: {=IF(VALUE(SUBSTITUTE(T$51,"M",""))<$E26,0,IFERROR(INDEX('Hiring & Compensation Plan'!$E$14:$V$14,1,VALUE(SUBSTITUTE(T$51,"M",""))-$E26+VALUE(SUBSTITUTE($C26,"M",""))),0)*IF($F26=0,0,$H26/$F26))} -> 6722.08 | U78: =SUM(C78:T78) -> 104192.24
A79: DALI | B79: 0 | C79: {=IF(VALUE(SUBSTITUTE(C$51,"M",""))<$E27,0,IFERROR(INDEX('Hiring & Compensation Plan'!$E$19:$V$19,1,VALUE(SUBSTITUTE(C$51,"M",""))-$E27+VALUE(SUBSTITUTE($C27,"M",""))),0)*IF($F27=0,0,$H27/$F27))} -> 0 | D79: {=IF(VALUE(SUBSTITUTE(D$51,"M",""))<$E27,0,IFERROR(INDEX('Hiring & Compensation Plan'!$E$19:$V$19,1,VALUE(SUBSTITUTE(D$51,"M",""))-$E27+VALUE(SUBSTITUTE($C27,"M",""))),0)*IF($F27=0,0,$H27/$F27))} -> 1212 | E79: {=IF(VALUE(SUBSTITUTE(E$51,"M",""))<$E27,0,IFERROR(INDEX('Hiring & Compensation Plan'!$E$19:$V$19,1,VALUE(SUBSTITUTE(E$51,"M",""))-$E27+VALUE(SUBSTITUTE($C27,"M",""))),0)*IF($F27=0,0,$H27/$F27))} -> 1212 | F79: {=IF(VALUE(SUBSTITUTE(F$51,"M",""))<$E27,0,IFERROR(INDEX('Hiring & Compensation Plan'!$E$19:$V$19,1,VALUE(SUBSTITUTE(F$51,"M",""))-$E27+VALUE(SUBSTITUTE($C27,"M",""))),0)*IF($F27=0,0,$H27/$F27))} -> 3361.04 | G79: {=IF(VALUE(SUBSTITUTE(G$51,"M",""))<$E27,0,IFERROR(INDEX('Hiring & Compensation Plan'!$E$19:$V$19,1,VALUE(SUBSTITUTE(G$51,"M",""))-$E27+VALUE(SUBSTITUTE($C27,"M",""))),0)*IF($F27=0,0,$H27/$F27))} -> 3361.04 | H79: {=IF(VALUE(SUBSTITUTE(H$51,"M",""))<$E27,0,IFERROR(INDEX('Hiring & Compensation Plan'!$E$19:$V$19,1,VALUE(SUBSTITUTE(H$51,"M",""))-$E27+VALUE(SUBSTITUTE($C27,"M",""))),0)*IF($F27=0,0,$H27/$F27))} -> 4201.3 | I79: {=IF(VALUE(SUBSTITUTE(I$51,"M",""))<$E27,0,IFERROR(INDEX('Hiring & Compensation Plan'!$E$19:$V$19,1,VALUE(SUBSTITUTE(I$51,"M",""))-$E27+VALUE(SUBSTITUTE($C27,"M",""))),0)*IF($F27=0,0,$H27/$F27))} -> 4201.3 | J79: {=IF(VALUE(SUBSTITUTE(J$51,"M",""))<$E27,0,IFERROR(INDEX('Hiring & Compensation Plan'!$E$19:$V$19,1,VALUE(SUBSTITUTE(J$51,"M",""))-$E27+VALUE(SUBSTITUTE($C27,"M",""))),0)*IF($F27=0,0,$H27/$F27))} -> 4201.3 | ... T79: {=IF(VALUE(SUBSTITUTE(T$51,"M",""))<$E27,0,IFERROR(INDEX('Hiring & Compensation Plan'!$E$19:$V$19,1,VALUE(SUBSTITUTE(T$51,"M",""))-$E27+VALUE(SUBSTITUTE($C27,"M",""))),0)*IF($F27=0,0,$H27/$F27))} -> 4201.3 | U79: =SUM(C79:T79) -> 63762.98
A80: NADR | B80: 0 | C80: {=IF(VALUE(SUBSTITUTE(C$51,"M",""))<$E28,0,IFERROR(INDEX('Hiring & Compensation Plan'!$E$24:$V$24,1,VALUE(SUBSTITUTE(C$51,"M",""))-$E28+VALUE(SUBSTITUTE($C28,"M",""))),0)*IF($F28=0,0,$H28/$F28))} -> 0 | D80: {=IF(VALUE(SUBSTITUTE(D$51,"M",""))<$E28,0,IFERROR(INDEX('Hiring & Compensation Plan'!$E$24:$V$24,1,VALUE(SUBSTITUTE(D$51,"M",""))-$E28+VALUE(SUBSTITUTE($C28,"M",""))),0)*IF($F28=0,0,$H28/$F28))} -> 0 | E80: {=IF(VALUE(SUBSTITUTE(E$51,"M",""))<$E28,0,IFERROR(INDEX('Hiring & Compensation Plan'!$E$24:$V$24,1,VALUE(SUBSTITUTE(E$51,"M",""))-$E28+VALUE(SUBSTITUTE($C28,"M",""))),0)*IF($F28=0,0,$H28/$F28))} -> 0 | F80: {=IF(VALUE(SUBSTITUTE(F$51,"M",""))<$E28,0,IFERROR(INDEX('Hiring & Compensation Plan'!$E$24:$V$24,1,VALUE(SUBSTITUTE(F$51,"M",""))-$E28+VALUE(SUBSTITUTE($C28,"M",""))),0)*IF($F28=0,0,$H28/$F28))} -> 0 | G80: {=IF(VALUE(SUBSTITUTE(G$51,"M",""))<$E28,0,IFERROR(INDEX('Hiring & Compensation Plan'!$E$24:$V$24,1,VALUE(SUBSTITUTE(G$51,"M",""))-$E28+VALUE(SUBSTITUTE($C28,"M",""))),0)*IF($F28=0,0,$H28/$F28))} -> 3361.04 | H80: {=IF(VALUE(SUBSTITUTE(H$51,"M",""))<$E28,0,IFERROR(INDEX('Hiring & Compensation Plan'!$E$24:$V$24,1,VALUE(SUBSTITUTE(H$51,"M",""))-$E28+VALUE(SUBSTITUTE($C28,"M",""))),0)*IF($F28=0,0,$H28/$F28))} -> 4201.3 | I80: {=IF(VALUE(SUBSTITUTE(I$51,"M",""))<$E28,0,IFERROR(INDEX('Hiring & Compensation Plan'!$E$24:$V$24,1,VALUE(SUBSTITUTE(I$51,"M",""))-$E28+VALUE(SUBSTITUTE($C28,"M",""))),0)*IF($F28=0,0,$H28/$F28))} -> 4201.3 | J80: {=IF(VALUE(SUBSTITUTE(J$51,"M",""))<$E28,0,IFERROR(INDEX('Hiring & Compensation Plan'!$E$24:$V$24,1,VALUE(SUBSTITUTE(J$51,"M",""))-$E28+VALUE(SUBSTITUTE($C28,"M",""))),0)*IF($F28=0,0,$H28/$F28))} -> 5041.56 | ... T80: {=IF(VALUE(SUBSTITUTE(T$51,"M",""))<$E28,0,IFERROR(INDEX('Hiring & Compensation Plan'!$E$24:$V$24,1,VALUE(SUBSTITUTE(T$51,"M",""))-$E28+VALUE(SUBSTITUTE($C28,"M",""))),0)*IF($F28=0,0,$H28/$F28))} -> 5041.56 | U80: =SUM(C80:T80) -> 67220.8
A81: MAXM | B81: 0 | C81: {=IF(VALUE(SUBSTITUTE(C$51,"M",""))<$E29,0,IFERROR(INDEX('Hiring & Compensation Plan'!$E$25:$V$25,1,VALUE(SUBSTITUTE(C$51,"M",""))-$E29+VALUE(SUBSTITUTE($C29,"M",""))),0)*IF($F29=0,0,$H29/$F29))} -> 2250 | D81: {=IF(VALUE(SUBSTITUTE(D$51,"M",""))<$E29,0,IFERROR(INDEX('Hiring & Compensation Plan'!$E$25:$V$25,1,VALUE(SUBSTITUTE(D$51,"M",""))-$E29+VALUE(SUBSTITUTE($C29,"M",""))),0)*IF($F29=0,0,$H29/$F29))} -> 0 | E81: {=IF(VALUE(SUBSTITUTE(E$51,"M",""))<$E29,0,IFERROR(INDEX('Hiring & Compensation Plan'!$E$25:$V$25,1,VALUE(SUBSTITUTE(E$51,"M",""))-$E29+VALUE(SUBSTITUTE($C29,"M",""))),0)*IF($F29=0,0,$H29/$F29))} -> 2250 | F81: {=IF(VALUE(SUBSTITUTE(F$51,"M",""))<$E29,0,IFERROR(INDEX('Hiring & Compensation Plan'!$E$25:$V$25,1,VALUE(SUBSTITUTE(F$51,"M",""))-$E29+VALUE(SUBSTITUTE($C29,"M",""))),0)*IF($F29=0,0,$H29/$F29))} -> 0 | G81: {=IF(VALUE(SUBSTITUTE(G$51,"M",""))<$E29,0,IFERROR(INDEX('Hiring & Compensation Plan'!$E$25:$V$25,1,VALUE(SUBSTITUTE(G$51,"M",""))-$E29+VALUE(SUBSTITUTE($C29,"M",""))),0)*IF($F29=0,0,$H29/$F29))} -> 2250 | H81: {=IF(VALUE(SUBSTITUTE(H$51,"M",""))<$E29,0,IFERROR(INDEX('Hiring & Compensation Plan'!$E$25:$V$25,1,VALUE(SUBSTITUTE(H$51,"M",""))-$E29+VALUE(SUBSTITUTE($C29,"M",""))),0)*IF($F29=0,0,$H29/$F29))} -> 0 | I81: {=IF(VALUE(SUBSTITUTE(I$51,"M",""))<$E29,0,IFERROR(INDEX('Hiring & Compensation Plan'!$E$25:$V$25,1,VALUE(SUBSTITUTE(I$51,"M",""))-$E29+VALUE(SUBSTITUTE($C29,"M",""))),0)*IF($F29=0,0,$H29/$F29))} -> 0 | J81: {=IF(VALUE(SUBSTITUTE(J$51,"M",""))<$E29,0,IFERROR(INDEX('Hiring & Compensation Plan'!$E$25:$V$25,1,VALUE(SUBSTITUTE(J$51,"M",""))-$E29+VALUE(SUBSTITUTE($C29,"M",""))),0)*IF($F29=0,0,$H29/$F29))} -> 2250 | ... T81: {=IF(VALUE(SUBSTITUTE(T$51,"M",""))<$E29,0,IFERROR(INDEX('Hiring & Compensation Plan'!$E$25:$V$25,1,VALUE(SUBSTITUTE(T$51,"M",""))-$E29+VALUE(SUBSTITUTE($C29,"M",""))),0)*IF($F29=0,0,$H29/$F29))} -> 0 | U81: =SUM(C81:T81) -> 13500
A82: TEAM PAYROLL — SCENARIO TOTAL | B82: =SUM(B77:B81) -> 0 | C82: =SUM(C77:C81) -> 5611.04 | D82: =SUM(D77:D81) -> 9614.6 | E82: =SUM(E77:E81) -> 11864.6 | F82: =SUM(F77:F81) -> 13444.16 | G82: =SUM(G77:G81) -> 19055.2 | H82: =SUM(H77:H81) -> 20166.24 | I82: =SUM(I77:I81) -> 20166.24 | ... T82: =SUM(T77:T81) -> 21006.5 | U82: =SUM(C82:T82) -> 337743.58
A83: CALCULATION SUPPORT — INFRASTRUCTURE MONTHLY PROFILES
A84: Capture Hardware | B84: 0 | C84: {=IF(AND(VALUE(SUBSTITUTE(C$51,"M",""))-IF($F35="",0,$F35)>=1,VALUE(SUBSTITUTE(C$51,"M",""))-IF($F35="",0,$F35)<=18),INDEX('MVP & lab hardware BOM'!$D$18:$U$18,1,VALUE(SUBSTITUTE(C$51,"M",""))-IF($F35="",0,$F35))*IF($C35=0,0,$E35/$C35),0)} -> 25589 | D84: {=IF(AND(VALUE(SUBSTITUTE(D$51,"M",""))-IF($F35="",0,$F35)>=1,VALUE(SUBSTITUTE(D$51,"M",""))-IF($F35="",0,$F35)<=18),INDEX('MVP & lab hardware BOM'!$D$18:$U$18,1,VALUE(SUBSTITUTE(D$51,"M",""))-IF($F35="",0,$F35))*IF($C35=0,0,$E35/$C35),0)} -> 0 | E84: {=IF(AND(VALUE(SUBSTITUTE(E$51,"M",""))-IF($F35="",0,$F35)>=1,VALUE(SUBSTITUTE(E$51,"M",""))-IF($F35="",0,$F35)<=18),INDEX('MVP & lab hardware BOM'!$D$18:$U$18,1,VALUE(SUBSTITUTE(E$51,"M",""))-IF($F35="",0,$F35))*IF($C35=0,0,$E35/$C35),0)} -> 0 | F84: {=IF(AND(VALUE(SUBSTITUTE(F$51,"M",""))-IF($F35="",0,$F35)>=1,VALUE(SUBSTITUTE(F$51,"M",""))-IF($F35="",0,$F35)<=18),INDEX('MVP & lab hardware BOM'!$D$18:$U$18,1,VALUE(SUBSTITUTE(F$51,"M",""))-IF($F35="",0,$F35))*IF($C35=0,0,$E35/$C35),0)} -> 1500 | G84: {=IF(AND(VALUE(SUBSTITUTE(G$51,"M",""))-IF($F35="",0,$F35)>=1,VALUE(SUBSTITUTE(G$51,"M",""))-IF($F35="",0,$F35)<=18),INDEX('MVP & lab hardware BOM'!$D$18:$U$18,1,VALUE(SUBSTITUTE(G$51,"M",""))-IF($F35="",0,$F35))*IF($C35=0,0,$E35/$C35),0)} -> 0 | H84: {=IF(AND(VALUE(SUBSTITUTE(H$51,"M",""))-IF($F35="",0,$F35)>=1,VALUE(SUBSTITUTE(H$51,"M",""))-IF($F35="",0,$F35)<=18),INDEX('MVP & lab hardware BOM'!$D$18:$U$18,1,VALUE(SUBSTITUTE(H$51,"M",""))-IF($F35="",0,$F35))*IF($C35=0,0,$E35/$C35),0)} -> 0 | I84: {=IF(AND(VALUE(SUBSTITUTE(I$51,"M",""))-IF($F35="",0,$F35)>=1,VALUE(SUBSTITUTE(I$51,"M",""))-IF($F35="",0,$F35)<=18),INDEX('MVP & lab hardware BOM'!$D$18:$U$18,1,VALUE(SUBSTITUTE(I$51,"M",""))-IF($F35="",0,$F35))*IF($C35=0,0,$E35/$C35),0)} -> 0 | J84: {=IF(AND(VALUE(SUBSTITUTE(J$51,"M",""))-IF($F35="",0,$F35)>=1,VALUE(SUBSTITUTE(J$51,"M",""))-IF($F35="",0,$F35)<=18),INDEX('MVP & lab hardware BOM'!$D$18:$U$18,1,VALUE(SUBSTITUTE(J$51,"M",""))-IF($F35="",0,$F35))*IF($C35=0,0,$E35/$C35),0)} -> 0 | ... T84: {=IF(AND(VALUE(SUBSTITUTE(T$51,"M",""))-IF($F35="",0,$F35)>=1,VALUE(SUBSTITUTE(T$51,"M",""))-IF($F35="",0,$F35)<=18),INDEX('MVP & lab hardware BOM'!$D$18:$U$18,1,VALUE(SUBSTITUTE(T$51,"M",""))-IF($F35="",0,$F35))*IF($C35=0,0,$E35/$C35),0)} -> 0 | U84: =SUM(C84:T84) -> 27379
A85: Shared Dataset Storage | B85: 0 | C85: {=IF(AND(VALUE(SUBSTITUTE(C$51,"M",""))-IF($F36="",0,$F36)>=1,VALUE(SUBSTITUTE(C$51,"M",""))-IF($F36="",0,$F36)<=18),INDEX('MVP & lab hardware BOM'!$D$24:$U$24,1,VALUE(SUBSTITUTE(C$51,"M",""))-IF($F36="",0,$F36))*IF($C36=0,0,$E36/$C36),0)} -> 1300 | D85: {=IF(AND(VALUE(SUBSTITUTE(D$51,"M",""))-IF($F36="",0,$F36)>=1,VALUE(SUBSTITUTE(D$51,"M",""))-IF($F36="",0,$F36)<=18),INDEX('MVP & lab hardware BOM'!$D$24:$U$24,1,VALUE(SUBSTITUTE(D$51,"M",""))-IF($F36="",0,$F36))*IF($C36=0,0,$E36/$C36),0)} -> 0 | E85: {=IF(AND(VALUE(SUBSTITUTE(E$51,"M",""))-IF($F36="",0,$F36)>=1,VALUE(SUBSTITUTE(E$51,"M",""))-IF($F36="",0,$F36)<=18),INDEX('MVP & lab hardware BOM'!$D$24:$U$24,1,VALUE(SUBSTITUTE(E$51,"M",""))-IF($F36="",0,$F36))*IF($C36=0,0,$E36/$C36),0)} -> 0 | F85: {=IF(AND(VALUE(SUBSTITUTE(F$51,"M",""))-IF($F36="",0,$F36)>=1,VALUE(SUBSTITUTE(F$51,"M",""))-IF($F36="",0,$F36)<=18),INDEX('MVP & lab hardware BOM'!$D$24:$U$24,1,VALUE(SUBSTITUTE(F$51,"M",""))-IF($F36="",0,$F36))*IF($C36=0,0,$E36/$C36),0)} -> 0 | G85: {=IF(AND(VALUE(SUBSTITUTE(G$51,"M",""))-IF($F36="",0,$F36)>=1,VALUE(SUBSTITUTE(G$51,"M",""))-IF($F36="",0,$F36)<=18),INDEX('MVP & lab hardware BOM'!$D$24:$U$24,1,VALUE(SUBSTITUTE(G$51,"M",""))-IF($F36="",0,$F36))*IF($C36=0,0,$E36/$C36),0)} -> 0 | H85: {=IF(AND(VALUE(SUBSTITUTE(H$51,"M",""))-IF($F36="",0,$F36)>=1,VALUE(SUBSTITUTE(H$51,"M",""))-IF($F36="",0,$F36)<=18),INDEX('MVP & lab hardware BOM'!$D$24:$U$24,1,VALUE(SUBSTITUTE(H$51,"M",""))-IF($F36="",0,$F36))*IF($C36=0,0,$E36/$C36),0)} -> 0 | I85: {=IF(AND(VALUE(SUBSTITUTE(I$51,"M",""))-IF($F36="",0,$F36)>=1,VALUE(SUBSTITUTE(I$51,"M",""))-IF($F36="",0,$F36)<=18),INDEX('MVP & lab hardware BOM'!$D$24:$U$24,1,VALUE(SUBSTITUTE(I$51,"M",""))-IF($F36="",0,$F36))*IF($C36=0,0,$E36/$C36),0)} -> 0 | J85: {=IF(AND(VALUE(SUBSTITUTE(J$51,"M",""))-IF($F36="",0,$F36)>=1,VALUE(SUBSTITUTE(J$51,"M",""))-IF($F36="",0,$F36)<=18),INDEX('MVP & lab hardware BOM'!$D$24:$U$24,1,VALUE(SUBSTITUTE(J$51,"M",""))-IF($F36="",0,$F36))*IF($C36=0,0,$E36/$C36),0)} -> 0 | ... T85: {=IF(AND(VALUE(SUBSTITUTE(T$51,"M",""))-IF($F36="",0,$F36)>=1,VALUE(SUBSTITUTE(T$51,"M",""))-IF($F36="",0,$F36)<=18),INDEX('MVP & lab hardware BOM'!$D$24:$U$24,1,VALUE(SUBSTITUTE(T$51,"M",""))-IF($F36="",0,$F36))*IF($C36=0,0,$E36/$C36),0)} -> 0 | U85: =SUM(C85:T85) -> 1300
A86: Development Compute | B86: 0 | C86: {=IF(AND(VALUE(SUBSTITUTE(C$51,"M",""))-IF($F37="",0,$F37)>=1,VALUE(SUBSTITUTE(C$51,"M",""))-IF($F37="",0,$F37)<=18),INDEX('MVP & lab hardware BOM'!$D$40:$U$40,1,VALUE(SUBSTITUTE(C$51,"M",""))-IF($F37="",0,$F37))*IF($C37=0,0,$E37/$C37),0)} -> 9880 | D86: {=IF(AND(VALUE(SUBSTITUTE(D$51,"M",""))-IF($F37="",0,$F37)>=1,VALUE(SUBSTITUTE(D$51,"M",""))-IF($F37="",0,$F37)<=18),INDEX('MVP & lab hardware BOM'!$D$40:$U$40,1,VALUE(SUBSTITUTE(D$51,"M",""))-IF($F37="",0,$F37))*IF($C37=0,0,$E37/$C37),0)} -> 0 | E86: {=IF(AND(VALUE(SUBSTITUTE(E$51,"M",""))-IF($F37="",0,$F37)>=1,VALUE(SUBSTITUTE(E$51,"M",""))-IF($F37="",0,$F37)<=18),INDEX('MVP & lab hardware BOM'!$D$40:$U$40,1,VALUE(SUBSTITUTE(E$51,"M",""))-IF($F37="",0,$F37))*IF($C37=0,0,$E37/$C37),0)} -> 0 | F86: {=IF(AND(VALUE(SUBSTITUTE(F$51,"M",""))-IF($F37="",0,$F37)>=1,VALUE(SUBSTITUTE(F$51,"M",""))-IF($F37="",0,$F37)<=18),INDEX('MVP & lab hardware BOM'!$D$40:$U$40,1,VALUE(SUBSTITUTE(F$51,"M",""))-IF($F37="",0,$F37))*IF($C37=0,0,$E37/$C37),0)} -> 0 | G86: {=IF(AND(VALUE(SUBSTITUTE(G$51,"M",""))-IF($F37="",0,$F37)>=1,VALUE(SUBSTITUTE(G$51,"M",""))-IF($F37="",0,$F37)<=18),INDEX('MVP & lab hardware BOM'!$D$40:$U$40,1,VALUE(SUBSTITUTE(G$51,"M",""))-IF($F37="",0,$F37))*IF($C37=0,0,$E37/$C37),0)} -> 0 | H86: {=IF(AND(VALUE(SUBSTITUTE(H$51,"M",""))-IF($F37="",0,$F37)>=1,VALUE(SUBSTITUTE(H$51,"M",""))-IF($F37="",0,$F37)<=18),INDEX('MVP & lab hardware BOM'!$D$40:$U$40,1,VALUE(SUBSTITUTE(H$51,"M",""))-IF($F37="",0,$F37))*IF($C37=0,0,$E37/$C37),0)} -> 0 | I86: {=IF(AND(VALUE(SUBSTITUTE(I$51,"M",""))-IF($F37="",0,$F37)>=1,VALUE(SUBSTITUTE(I$51,"M",""))-IF($F37="",0,$F37)<=18),INDEX('MVP & lab hardware BOM'!$D$40:$U$40,1,VALUE(SUBSTITUTE(I$51,"M",""))-IF($F37="",0,$F37))*IF($C37=0,0,$E37/$C37),0)} -> 0 | J86: {=IF(AND(VALUE(SUBSTITUTE(J$51,"M",""))-IF($F37="",0,$F37)>=1,VALUE(SUBSTITUTE(J$51,"M",""))-IF($F37="",0,$F37)<=18),INDEX('MVP & lab hardware BOM'!$D$40:$U$40,1,VALUE(SUBSTITUTE(J$51,"M",""))-IF($F37="",0,$F37))*IF($C37=0,0,$E37/$C37),0)} -> 0 | ... T86: {=IF(AND(VALUE(SUBSTITUTE(T$51,"M",""))-IF($F37="",0,$F37)>=1,VALUE(SUBSTITUTE(T$51,"M",""))-IF($F37="",0,$F37)<=18),INDEX('MVP & lab hardware BOM'!$D$40:$U$40,1,VALUE(SUBSTITUTE(T$51,"M",""))-IF($F37="",0,$F37))*IF($C37=0,0,$E37/$C37),0)} -> 0 | U86: =SUM(C86:T86) -> 9880
A87: Embedded AI Compute | B87: 0 | C87: {=IF(AND(VALUE(SUBSTITUTE(C$51,"M",""))-IF($F38="",0,$F38)>=1,VALUE(SUBSTITUTE(C$51,"M",""))-IF($F38="",0,$F38)<=18),INDEX('MVP & lab hardware BOM'!$D$53:$U$53,1,VALUE(SUBSTITUTE(C$51,"M",""))-IF($F38="",0,$F38))*IF($C38=0,0,$E38/$C38),0)} -> 0 | D87: {=IF(AND(VALUE(SUBSTITUTE(D$51,"M",""))-IF($F38="",0,$F38)>=1,VALUE(SUBSTITUTE(D$51,"M",""))-IF($F38="",0,$F38)<=18),INDEX('MVP & lab hardware BOM'!$D$53:$U$53,1,VALUE(SUBSTITUTE(D$51,"M",""))-IF($F38="",0,$F38))*IF($C38=0,0,$E38/$C38),0)} -> 0 | E87: {=IF(AND(VALUE(SUBSTITUTE(E$51,"M",""))-IF($F38="",0,$F38)>=1,VALUE(SUBSTITUTE(E$51,"M",""))-IF($F38="",0,$F38)<=18),INDEX('MVP & lab hardware BOM'!$D$53:$U$53,1,VALUE(SUBSTITUTE(E$51,"M",""))-IF($F38="",0,$F38))*IF($C38=0,0,$E38/$C38),0)} -> 0 | F87: {=IF(AND(VALUE(SUBSTITUTE(F$51,"M",""))-IF($F38="",0,$F38)>=1,VALUE(SUBSTITUTE(F$51,"M",""))-IF($F38="",0,$F38)<=18),INDEX('MVP & lab hardware BOM'!$D$53:$U$53,1,VALUE(SUBSTITUTE(F$51,"M",""))-IF($F38="",0,$F38))*IF($C38=0,0,$E38/$C38),0)} -> 5239 | G87: {=IF(AND(VALUE(SUBSTITUTE(G$51,"M",""))-IF($F38="",0,$F38)>=1,VALUE(SUBSTITUTE(G$51,"M",""))-IF($F38="",0,$F38)<=18),INDEX('MVP & lab hardware BOM'!$D$53:$U$53,1,VALUE(SUBSTITUTE(G$51,"M",""))-IF($F38="",0,$F38))*IF($C38=0,0,$E38/$C38),0)} -> 0 | H87: {=IF(AND(VALUE(SUBSTITUTE(H$51,"M",""))-IF($F38="",0,$F38)>=1,VALUE(SUBSTITUTE(H$51,"M",""))-IF($F38="",0,$F38)<=18),INDEX('MVP & lab hardware BOM'!$D$53:$U$53,1,VALUE(SUBSTITUTE(H$51,"M",""))-IF($F38="",0,$F38))*IF($C38=0,0,$E38/$C38),0)} -> 0 | I87: {=IF(AND(VALUE(SUBSTITUTE(I$51,"M",""))-IF($F38="",0,$F38)>=1,VALUE(SUBSTITUTE(I$51,"M",""))-IF($F38="",0,$F38)<=18),INDEX('MVP & lab hardware BOM'!$D$53:$U$53,1,VALUE(SUBSTITUTE(I$51,"M",""))-IF($F38="",0,$F38))*IF($C38=0,0,$E38/$C38),0)} -> 0 | J87: {=IF(AND(VALUE(SUBSTITUTE(J$51,"M",""))-IF($F38="",0,$F38)>=1,VALUE(SUBSTITUTE(J$51,"M",""))-IF($F38="",0,$F38)<=18),INDEX('MVP & lab hardware BOM'!$D$53:$U$53,1,VALUE(SUBSTITUTE(J$51,"M",""))-IF($F38="",0,$F38))*IF($C38=0,0,$E38/$C38),0)} -> 0 | ... T87: {=IF(AND(VALUE(SUBSTITUTE(T$51,"M",""))-IF($F38="",0,$F38)>=1,VALUE(SUBSTITUTE(T$51,"M",""))-IF($F38="",0,$F38)<=18),INDEX('MVP & lab hardware BOM'!$D$53:$U$53,1,VALUE(SUBSTITUTE(T$51,"M",""))-IF($F38="",0,$F38))*IF($C38=0,0,$E38/$C38),0)} -> 0 | U87: =SUM(C87:T87) -> 11538
A88: Lab Operations & Risk | B88: 0 | C88: {=IF(AND(VALUE(SUBSTITUTE(C$51,"M",""))-IF($F39="",0,$F39)>=1,VALUE(SUBSTITUTE(C$51,"M",""))-IF($F39="",0,$F39)<=18),INDEX('MVP & lab hardware BOM'!$D$60:$U$60,1,VALUE(SUBSTITUTE(C$51,"M",""))-IF($F39="",0,$F39))*IF($C39=0,0,$E39/$C39),0)} -> 694.44 | D88: {=IF(AND(VALUE(SUBSTITUTE(D$51,"M",""))-IF($F39="",0,$F39)>=1,VALUE(SUBSTITUTE(D$51,"M",""))-IF($F39="",0,$F39)<=18),INDEX('MVP & lab hardware BOM'!$D$60:$U$60,1,VALUE(SUBSTITUTE(D$51,"M",""))-IF($F39="",0,$F39))*IF($C39=0,0,$E39/$C39),0)} -> 194.44 | E88: {=IF(AND(VALUE(SUBSTITUTE(E$51,"M",""))-IF($F39="",0,$F39)>=1,VALUE(SUBSTITUTE(E$51,"M",""))-IF($F39="",0,$F39)<=18),INDEX('MVP & lab hardware BOM'!$D$60:$U$60,1,VALUE(SUBSTITUTE(E$51,"M",""))-IF($F39="",0,$F39))*IF($C39=0,0,$E39/$C39),0)} -> 194.44 | F88: {=IF(AND(VALUE(SUBSTITUTE(F$51,"M",""))-IF($F39="",0,$F39)>=1,VALUE(SUBSTITUTE(F$51,"M",""))-IF($F39="",0,$F39)<=18),INDEX('MVP & lab hardware BOM'!$D$60:$U$60,1,VALUE(SUBSTITUTE(F$51,"M",""))-IF($F39="",0,$F39))*IF($C39=0,0,$E39/$C39),0)} -> 994.44 | G88: {=IF(AND(VALUE(SUBSTITUTE(G$51,"M",""))-IF($F39="",0,$F39)>=1,VALUE(SUBSTITUTE(G$51,"M",""))-IF($F39="",0,$F39)<=18),INDEX('MVP & lab hardware BOM'!$D$60:$U$60,1,VALUE(SUBSTITUTE(G$51,"M",""))-IF($F39="",0,$F39))*IF($C39=0,0,$E39/$C39),0)} -> 194.44 | H88: {=IF(AND(VALUE(SUBSTITUTE(H$51,"M",""))-IF($F39="",0,$F39)>=1,VALUE(SUBSTITUTE(H$51,"M",""))-IF($F39="",0,$F39)<=18),INDEX('MVP & lab hardware BOM'!$D$60:$U$60,1,VALUE(SUBSTITUTE(H$51,"M",""))-IF($F39="",0,$F39))*IF($C39=0,0,$E39/$C39),0)} -> 194.44 | I88: {=IF(AND(VALUE(SUBSTITUTE(I$51,"M",""))-IF($F39="",0,$F39)>=1,VALUE(SUBSTITUTE(I$51,"M",""))-IF($F39="",0,$F39)<=18),INDEX('MVP & lab hardware BOM'!$D$60:$U$60,1,VALUE(SUBSTITUTE(I$51,"M",""))-IF($F39="",0,$F39))*IF($C39=0,0,$E39/$C39),0)} -> 194.44 | J88: {=IF(AND(VALUE(SUBSTITUTE(J$51,"M",""))-IF($F39="",0,$F39)>=1,VALUE(SUBSTITUTE(J$51,"M",""))-IF($F39="",0,$F39)<=18),INDEX('MVP & lab hardware BOM'!$D$60:$U$60,1,VALUE(SUBSTITUTE(J$51,"M",""))-IF($F39="",0,$F39))*IF($C39=0,0,$E39/$C39),0)} -> 194.44 | ... T88: {=IF(AND(VALUE(SUBSTITUTE(T$51,"M",""))-IF($F39="",0,$F39)>=1,VALUE(SUBSTITUTE(T$51,"M",""))-IF($F39="",0,$F39)<=18),INDEX('MVP & lab hardware BOM'!$D$60:$U$60,1,VALUE(SUBSTITUTE(T$51,"M",""))-IF($F39="",0,$F39))*IF($C39=0,0,$E39/$C39),0)} -> 194.52 | U88: =SUM(C88:T88) -> 4800
A89: Cloud Compute (OpEx) | B89: 0 | C89: {=IF(AND(VALUE(SUBSTITUTE(C$51,"M",""))-IF($F40="",0,$F40)>=1,VALUE(SUBSTITUTE(C$51,"M",""))-IF($F40="",0,$F40)<=18),INDEX('MVP & lab hardware BOM'!$D$68:$U$68,1,VALUE(SUBSTITUTE(C$51,"M",""))-IF($F40="",0,$F40))*IF($C40=0,0,$E40/$C40),0)} -> 103.14 | D89: {=IF(AND(VALUE(SUBSTITUTE(D$51,"M",""))-IF($F40="",0,$F40)>=1,VALUE(SUBSTITUTE(D$51,"M",""))-IF($F40="",0,$F40)<=18),INDEX('MVP & lab hardware BOM'!$D$68:$U$68,1,VALUE(SUBSTITUTE(D$51,"M",""))-IF($F40="",0,$F40))*IF($C40=0,0,$E40/$C40),0)} -> 209.6 | E89: {=IF(AND(VALUE(SUBSTITUTE(E$51,"M",""))-IF($F40="",0,$F40)>=1,VALUE(SUBSTITUTE(E$51,"M",""))-IF($F40="",0,$F40)<=18),INDEX('MVP & lab hardware BOM'!$D$68:$U$68,1,VALUE(SUBSTITUTE(E$51,"M",""))-IF($F40="",0,$F40))*IF($C40=0,0,$E40/$C40),0)} -> 254.1 | F89: {=IF(AND(VALUE(SUBSTITUTE(F$51,"M",""))-IF($F40="",0,$F40)>=1,VALUE(SUBSTITUTE(F$51,"M",""))-IF($F40="",0,$F40)<=18),INDEX('MVP & lab hardware BOM'!$D$68:$U$68,1,VALUE(SUBSTITUTE(F$51,"M",""))-IF($F40="",0,$F40))*IF($C40=0,0,$E40/$C40),0)} -> 528.73 | G89: {=IF(AND(VALUE(SUBSTITUTE(G$51,"M",""))-IF($F40="",0,$F40)>=1,VALUE(SUBSTITUTE(G$51,"M",""))-IF($F40="",0,$F40)<=18),INDEX('MVP & lab hardware BOM'!$D$68:$U$68,1,VALUE(SUBSTITUTE(G$51,"M",""))-IF($F40="",0,$F40))*IF($C40=0,0,$E40/$C40),0)} -> 634.01 | H89: {=IF(AND(VALUE(SUBSTITUTE(H$51,"M",""))-IF($F40="",0,$F40)>=1,VALUE(SUBSTITUTE(H$51,"M",""))-IF($F40="",0,$F40)<=18),INDEX('MVP & lab hardware BOM'!$D$68:$U$68,1,VALUE(SUBSTITUTE(H$51,"M",""))-IF($F40="",0,$F40))*IF($C40=0,0,$E40/$C40),0)} -> 787.13 | I89: {=IF(AND(VALUE(SUBSTITUTE(I$51,"M",""))-IF($F40="",0,$F40)>=1,VALUE(SUBSTITUTE(I$51,"M",""))-IF($F40="",0,$F40)<=18),INDEX('MVP & lab hardware BOM'!$D$68:$U$68,1,VALUE(SUBSTITUTE(I$51,"M",""))-IF($F40="",0,$F40))*IF($C40=0,0,$E40/$C40),0)} -> 866.6 | J89: {=IF(AND(VALUE(SUBSTITUTE(J$51,"M",""))-IF($F40="",0,$F40)>=1,VALUE(SUBSTITUTE(J$51,"M",""))-IF($F40="",0,$F40)<=18),INDEX('MVP & lab hardware BOM'!$D$68:$U$68,1,VALUE(SUBSTITUTE(J$51,"M",""))-IF($F40="",0,$F40))*IF($C40=0,0,$E40/$C40),0)} -> 3625.99 | ... T89: {=IF(AND(VALUE(SUBSTITUTE(T$51,"M",""))-IF($F40="",0,$F40)>=1,VALUE(SUBSTITUTE(T$51,"M",""))-IF($F40="",0,$F40)<=18),INDEX('MVP & lab hardware BOM'!$D$68:$U$68,1,VALUE(SUBSTITUTE(T$51,"M",""))-IF($F40="",0,$F40))*IF($C40=0,0,$E40/$C40),0)} -> 1333.04 | U89: =SUM(C89:T89) -> 27000
A90: INFRASTRUCTURE — SCENARIO TOTAL | B90: =SUM(B84:B89) -> 0 | C90: =SUM(C84:C89) -> 37566.58 | D90: =SUM(D84:D89) -> 404.04 | E90: =SUM(E84:E89) -> 448.54 | F90: =SUM(F84:F89) -> 8262.17 | G90: =SUM(G84:G89) -> 828.45 | H90: =SUM(H84:H89) -> 981.57 | I90: =SUM(I84:I89) -> 1061.04 | ... T90: =SUM(T84:T89) -> 1527.56 | U90: =SUM(C90:T90) -> 81897
